[
    {
        "type": "INV",
        "text": "okay . \u00151140_1420\u0015",
        "mor": "co|okay .",
        "gra": "1|0|INCROOT 2|1|PUNCT",
        "wor": "okay \u00151140_1420\u0015 ."
    },
    {
        "type": "INV",
        "text": "okay . \u00156061_6321\u0015",
        "mor": "co|okay .",
        "gra": "1|0|INCROOT 2|1|PUNCT",
        "wor": "okay \u00156061_6321\u0015 ."
    },
    {
        "type": "INV",
        "text": "so ‡ the first question is I'm gonna ask you to do some talking . \u00156400_9790\u0015",
        "mor": "co|so beg|beg det:art|the adj|first n|question cop|be&3S",
        "gra": "1|0|BEG 2|1|BEGP 3|5|DET 4|5|MOD 5|6|SUBJ 6|0|ROOT 7|9|SUBJ 8|9|AUX",
        "wor": "so \u00156400_6510\u0015 ‡ the \u00156510_6650\u0015 first \u00156650_6870\u0015 question \u00156870_7190\u0015 is \u00157190_7450\u0015 I'm \u00158100_8300\u0015 gonna \u00158300_8420\u0015 ask \u00158420_8790\u0015 you \u00158790_8860\u0015 to \u00158860_8960\u0015 do \u00158960_9150\u0015 some \u00159150_9360\u0015 talking \u00159360_9790\u0015 ."
    },
    {
        "type": "INV",
        "text": "the first question is how do you think you do speaking English ? \u00159973_13333\u0015",
        "mor": "det:art|the adj|first n|question cop|be&3S pro:int|how mod|do",
        "gra": "1|3|DET 2|3|MOD 3|4|SUBJ 4|0|ROOT 5|8|JCT 6|8|AUX 7|8|SUBJ 8|4|CPRED",
        "wor": "the \u00159973_10293\u0015 first \u001510293_10513\u0015 question \u001510513_10863\u0015 is \u001510863_11223\u0015 how \u001511223_11413\u0015 do \u001511413_11493\u0015 you \u001511493_11623\u0015 think \u001511623_11943\u0015 you \u001511943_12033\u0015 do \u001512033_12253\u0015 speaking \u001512253_12743\u0015 English \u001512743_13333\u0015 ?"
    },
    {
        "type": "PAR",
        "text": "I think I speak well . \u001515428_17128\u0015",
        "mor": "pro:sub|I v|think pro:sub|I v|speak adv|well .",
        "gra": "1|2|SUBJ 2|0|ROOT 3|4|SUBJ 4|2|COMP 5|4|JCT 6|2|PUNCT",
        "wor": "I \u001515428_15538\u0015 think \u001515538_15808\u0015 I \u001515858_15948\u0015 speak \u001515948_16358\u0015 well \u001516798_17128\u0015 ."
    },
    {
        "type": "INV",
        "text": "okay . \u001518423_18643\u0015",
        "mor": "co|okay .",
        "gra": "1|0|INCROOT 2|1|PUNCT",
        "wor": "okay \u001518423_18643\u0015 ."
    },
    {
        "type": "PAR",
        "text": "yeah . \u001518902_19122\u0015",
        "mor": "co|yeah .",
        "gra": "1|0|INCROOT 2|1|PUNCT",
        "wor": "yeah \u001518902_19122\u0015 ."
    },
    {
        "type": "INV",
        "text": "okay ‡ good . \u001519429_20369\u0015",
        "mor": "co|okay beg|beg adj|good .",
        "gra": "1|0|BEG 2|1|BEGP 3|0|INCROOT 4|3|PUNCT",
        "wor": "okay \u001519429_19809\u0015 ‡ good \u001520089_20369\u0015 ."
    },
    {
        "type": "PAR",
        "text": "I [//] I_mean it has evolved &-uh it [//] in the last twenty eight years &*INV",
        "mor": "co|I_mean pro:per|it aux|have&3S part|evolve-PASTP prep|in",
        "gra": "1|4|COM 2|4|SUBJ 3|4|AUX 4|0|ROOT 5|4|JCT 6|8|DET 7|8|MOD 8|10|QUANT",
        "wor": "I [//] \u001521057_21397\u0015 I_mean \u001521427_21797\u0015 it \u001521797_21957\u0015 has \u001521957_22237\u0015 evolved \u001522237_22907\u0015 &-uh \u001522937_22947\u0015 it [//] \u001522947_23737\u0015 in \u001523737_24057\u0015 the \u001524057_24117\u0015 last \u001524117_24447\u0015 twenty \u001524447_24807\u0015 eight \u001524807_24947\u0015 years \u001524947_25327\u0015 &*INV:yeah &-uh \u001525327_26077\u0015 and \u001526187_26637\u0015 compared \u001526747_27457\u0015 to \u001527457_27537\u0015 when \u001527537_27667\u0015 I \u001527667_27737\u0015 came \u001527737_28067\u0015 in \u001528067_28187\u0015 nineteen \u001528187_28617\u0015 eighty \u001528617_28847\u0015 seven \u001528847_29517\u0015 ."
    },
    {
        "type": "PAR",
        "text": "so ‡ it has been a &+gra gradual +//. \u001530049_31859\u0015",
        "mor": "co|so beg|beg pro:per|it aux|have&3S aux|be&PASTP det:art|a",
        "gra": "1|0|BEG 2|1|BEGP 3|7|SUBJ 4|7|AUX 5|7|AUX 6|7|DET 7|0|INCROOT 8|7|PUNCT",
        "wor": "so \u001530049_30249\u0015 ‡ it \u001530249_30399\u0015 has \u001530399_30569\u0015 been \u001530569_30779\u0015 a \u001530779_30849\u0015 &+gra \u001530849_31269\u0015 gradual \u001531299_31859\u0015 +//."
    },
    {
        "type": "PAR",
        "text": "I useta speak English then and then even now . \u001531883_35253\u0015",
        "mor": "pro:sub|I mod|used~inf|to v|speak n:prop|English adv:tem|then",
        "gra": "1|4|SUBJ 2|4|AUX 3|4|INF 4|0|ROOT 5|4|OBJ 6|5|JCT 7|6|CONJ 8|10|JCT",
        "wor": "I \u001531883_32033\u0015 useta \u001532033_32383\u0015 speak \u001532383_32643\u0015 English \u001532643_33123\u0015 then \u001533123_33423\u0015 and \u001533423_33683\u0015 then \u001533683_34193\u0015 even \u001534503_34793\u0015 now \u001534793_35253\u0015 ."
    },
    {
        "type": "INV",
        "text": "mhm . \u001535307_35677\u0015",
        "mor": "co|mhm=yes .",
        "gra": "1|0|INCROOT 2|1|PUNCT",
        "wor": "mhm \u001535307_35677\u0015 ."
    },
    {
        "type": "PAR",
        "text": "but then I think the accent and the vocabulary has evolved . \u001535865_40145\u0015",
        "mor": "conj|but adv:tem|then pro:sub|I v|think det:art|the n|accent",
        "gra": "1|4|LINK 2|4|JCT 3|4|SUBJ 4|0|ROOT 5|6|DET 6|4|OBJ 7|11|LINK 8|9|DET",
        "wor": "but \u001535865_36115\u0015 then \u001536115_36285\u0015 I \u001536285_36395\u0015 think \u001536395_36685\u0015 the \u001536685_36695\u0015 accent \u001536695_37645\u0015 and \u001537645_37855\u0015 the \u001537855_37865\u0015 vocabulary \u001537865_39155\u0015 has \u001539155_39585\u0015 evolved \u001539585_40145\u0015 ."
    },
    {
        "type": "PAR",
        "text": "and &-hm it has conformed to the place and culture . \u001540200_44300\u0015",
        "mor": "coord|and pro:per|it aux|have&3S part|conform-PASTP prep|to",
        "gra": "1|4|LINK 2|4|SUBJ 3|4|AUX 4|0|ROOT 5|4|JCT 6|7|DET 7|5|POBJ 8|7|CONJ",
        "wor": "and \u001540200_40620\u0015 &-hm \u001540940_41370\u0015 it \u001541500_41720\u0015 has \u001541720_41920\u0015 conformed \u001541920_42560\u0015 to \u001542560_42930\u0015 the \u001543410_43420\u0015 place \u001543420_43700\u0015 and \u001543700_43880\u0015 culture \u001543880_44300\u0015 ."
    },
    {
        "type": "INV",
        "text": "good . \u001544623_44873\u0015",
        "mor": "adj|good .",
        "gra": "1|0|INCROOT 2|1|PUNCT",
        "wor": "good \u001544623_44873\u0015 ."
    },
    {
        "type": "PAR",
        "text": "I still may need to work more on it . \u001545057_46847\u0015",
        "mor": "pro:sub|I adv|still mod|may v|need prep|to n|work adv|more prep|on",
        "gra": "1|4|SUBJ 2|4|JCT 3|4|AUX 4|0|ROOT 5|4|JCT 6|5|POBJ 7|4|JCT 8|4|JCT",
        "wor": "I \u001545057_45257\u0015 still \u001545257_45597\u0015 may \u001545597_45757\u0015 need \u001545757_45987\u0015 to \u001545987_46167\u0015 work \u001546167_46357\u0015 more \u001546357_46547\u0015 on \u001546587_46777\u0015 it \u001546777_46847\u0015 ."
    },
    {
        "type": "PAR",
        "text": "I don't know . \u001546863_47563\u0015",
        "mor": "pro:sub|I mod|do~neg|not v|know .",
        "gra": "1|4|SUBJ 2|4|AUX 3|2|NEG 4|0|ROOT 5|4|PUNCT",
        "wor": "I \u001546863_46953\u0015 don't \u001546953_47383\u0015 know \u001547383_47563\u0015 ."
    },
    {
        "type": "PAR",
        "text": "<it's a> [//] it's an unconscious &-uh work . \u001547947_51277\u0015",
        "mor": "pro:per|it~cop|be&3S det:art|a n|unconscious n|work .",
        "gra": "1|2|SUBJ 2|0|ROOT 3|5|DET 4|5|MOD 5|2|PRED 6|2|PUNCT",
        "wor": "<it's \u001547947_48037\u0015 a \u001548037_48067\u0015> [//] it's an unconscious &-uh work . \u001548067_51277\u0015"
    },
    {
        "type": "INV",
        "text": "+< right . \u001550115_50205\u0015",
        "mor": "co|right .",
        "gra": "1|0|INCROOT 2|1|PUNCT",
        "wor": "+< right \u001550115_50205\u0015 ."
    },
    {
        "type": "PAR",
        "text": "so &=laughs +... \u001551311_51561\u0015",
        "mor": "co|so +...",
        "gra": "1|0|INCROOT 2|1|PUNCT",
        "wor": "so \u001551311_51561\u0015 &=laughs +..."
    },
    {
        "type": "INV",
        "text": "just from being here and talking with the people ? \u001551866_53916\u0015",
        "mor": "adv|just prep|from n:gerund|be-PRESP adv|here coord|and",
        "gra": "1|2|JCT 2|0|INCROOT 3|2|POBJ 4|3|JCT 5|3|CONJ 6|5|COORD 7|6|JCT 8|9|DET",
        "wor": "just \u001551866_52096\u0015 from \u001552096_52286\u0015 being \u001552286_52596\u0015 here \u001552596_52756\u0015 and \u001552756_52926\u0015 talking \u001552926_53306\u0015 with \u001553306_53606\u0015 the \u001553606_53616\u0015 people \u001553616_53916\u0015 ?"
    },
    {
        "type": "PAR",
        "text": "with the people and yes and day-to-day language „ yeah . \u001553939_57619\u0015",
        "mor": "prep|with det:art|the n|person&PL coord|and co|yes coord|and",
        "gra": "1|0|INCROOT 2|3|DET 3|1|POBJ 4|3|CONJ 5|4|COORD 6|3|CONJ 7|8|MOD",
        "wor": "with \u001553939_54319\u0015 the \u001554319_54329\u0015 people \u001554329_54619\u0015 and \u001554619_55209\u0015 yes \u001555209_55739\u0015 and \u001555739_55959\u0015 day-\u001555959_56089\u0015 to-\u001556089_56219\u0015 day \u001556219_56409\u0015 language \u001556409_57139\u0015 „ yeah \u001557199_57619\u0015 ."
    },
    {
        "type": "INV",
        "text": "+< okay . \u001558120_58200\u0015",
        "mor": "co|okay .",
        "gra": "1|0|INCROOT 2|1|PUNCT",
        "wor": "+< okay \u001558120_58200\u0015 ."
    },
    {
        "type": "INV",
        "text": "okay ‡ good . \u001558220_58840\u0015",
        "mor": "co|okay beg|beg adj|good .",
        "gra": "1|0|BEG 2|1|BEGP 3|0|INCROOT 4|3|PUNCT",
        "wor": "okay \u001558220_58480\u0015 ‡ good \u001558550_58840\u0015 ."
    },
    {
        "type": "INV",
        "text": "&-um do you speak any languages besides English ? \u001559494_62604\u0015",
        "mor": "mod|do pro:per|you v|speak qn|any n|language-PL prep|besides",
        "gra": "1|3|AUX 2|3|SUBJ 3|0|ROOT 4|5|QUANT 5|3|OBJ 6|3|JCT 7|6|POBJ 8|3|PUNCT",
        "wor": "&-um \u001559494_60024\u0015 do \u001560024_60214\u0015 you \u001560214_60324\u0015 speak \u001560324_60644\u0015 any \u001560644_60864\u0015 languages \u001560864_61404\u0015 besides \u001561404_61994\u0015 English \u001561994_62604\u0015 ?"
    },
    {
        "type": "PAR",
        "text": "it's Hindi [/] Hindi . \u001563588_65007\u0015",
        "mor": "pro:per|it~cop|be&3S n:prop|Hindi .",
        "gra": "1|2|SUBJ 2|0|ROOT 3|2|PRED 4|2|PUNCT",
        "wor": "it's \u001563588_63928\u0015 Hindi [/] \u001563928_64558\u0015 Hindi \u001564668_65008\u0015 ."
    },
    {
        "type": "PAR",
        "text": "and &-uh there's another language , Punjabi &*INV",
        "mor": "coord|and pro:exist|there~cop|be&3S qn|another n|language cm|cm",
        "gra": "1|3|LINK 2|3|SUBJ 3|0|ROOT 4|5|QUANT 5|3|PRED 6|3|LP 7|3|ENUM 8|7|LP",
        "wor": "and \u001565260_65520\u0015 &-uh \u001565520_65690\u0015 there's \u001565690_65960\u0015 another \u001565960_66340\u0015 language \u001566340_66720\u0015 , Punjabi \u001566720_67530\u0015 &*INV:okay , &-uh \u001568270_68700\u0015 in \u001568700_69360\u0015 India \u001569540_70350\u0015 which \u001570380_70590\u0015 is \u001570590_70780\u0015 similar \u001570780_71260\u0015 to \u001571260_71610\u0015 Hindi \u001571610_72250\u0015 ."
    },
    {
        "type": "PAR",
        "text": "so ‡ I could say I can speak and understand that one too . \u001572271_77251\u0015",
        "mor": "co|so beg|beg pro:sub|I mod|could v|say pro:sub|I mod|can v|speak",
        "gra": "1|0|BEG 2|1|BEGP 3|5|SUBJ 4|5|AUX 5|0|ROOT 6|8|SUBJ 7|8|AUX 8|5|COMP",
        "wor": "so \u001572271_72751\u0015 ‡ I \u001574221_74341\u0015 could \u001574341_74621\u0015 say \u001574621_74751\u0015 I \u001574751_74891\u0015 can \u001574891_75291\u0015 speak \u001575291_75861\u0015 and \u001575861_75981\u0015 understand \u001575981_76611\u0015 that \u001576611_76841\u0015 one \u001576841_77031\u0015 too \u001577031_77251\u0015 ."
    },
    {
        "type": "INV",
        "text": "okay ‡ &-um have you ever had a stroke or serious illness ? \u001577385_82465\u0015",
        "mor": "co|okay beg|beg v|have pro:per|you adv|ever v|have&PAST det:art|a",
        "gra": "1|0|BEG 2|1|BEGP 3|0|ROOT 4|3|OBJ 5|3|JCT 6|3|COMP 7|8|DET 8|6|OBJ",
        "wor": "okay \u001577385_77955\u0015 ‡ &-um \u001578625_79275\u0015 have \u001579575_79745\u0015 you \u001579745_79835\u0015 ever \u001579835_80315\u0015 had \u001580315_80565\u0015 a \u001580565_80695\u0015 stroke \u001580695_81315\u0015 or \u001581315_81435\u0015 serious \u001581435_82115\u0015 illness \u001582115_82465\u0015 ?"
    },
    {
        "type": "PAR",
        "text": "no . \u001583275_83535\u0015",
        "mor": "co|no .",
        "gra": "1|0|INCROOT 2|1|PUNCT",
        "wor": "no \u001583275_83535\u0015 ."
    },
    {
        "type": "INV",
        "text": "no ‡ okay . \u001583770_84430\u0015",
        "mor": "co|no beg|beg co|okay .",
        "gra": "1|0|BEG 2|1|BEGP 3|0|INCROOT 4|3|PUNCT",
        "wor": "no \u001583770_83960\u0015 ‡ okay \u001584180_84430\u0015 ."
    },
    {
        "type": "PAR",
        "text": "that's short &=laughs . \u001584768_85188\u0015",
        "mor": "pro:dem|that~cop|be&3S adj|short .",
        "gra": "1|2|SUBJ 2|0|ROOT 3|2|PRED 4|2|PUNCT",
        "wor": "that's \u001584768_84898\u0015 short \u001584898_85188\u0015 &=laughs ."
    },
    {
        "type": "INV",
        "text": "that's good &=laughs . \u001586053_87463\u0015",
        "mor": "pro:dem|that~cop|be&3S adj|good .",
        "gra": "1|2|SUBJ 2|0|ROOT 3|2|PRED 4|2|PUNCT",
        "wor": "that's \u001586053_86283\u0015 good \u001586283_87463\u0015 &=laughs ."
    },
    {
        "type": "INV",
        "text": "let's see . \u001588602_89232\u0015",
        "mor": "v|let~pro:obj|us v|see .",
        "gra": "1|0|ROOT 2|1|OBJ 3|1|COMP 4|1|PUNCT",
        "wor": "let's \u001588602_89002\u0015 see \u001589002_89232\u0015 ."
    },
    {
        "type": "INV",
        "text": "&-um I'm gonna skip a few of these . \u001590175_93775\u0015",
        "mor": "pro:sub|I~aux|be&1S part|go&PRESP~inf|to v|skip det:art|a qn|few",
        "gra": "1|3|SUBJ 2|3|AUX 3|0|ROOT 4|5|INF 5|3|COMP 6|7|DET 7|5|OBJ 8|7|NJCT",
        "wor": "&-um \u001590175_90875\u0015 I'm \u001592345_92485\u0015 gonna \u001592485_92605\u0015 skip \u001592605_92975\u0015 a \u001592975_93055\u0015 few \u001593145_93365\u0015 of \u001593415_93475\u0015 these \u001593475_93775\u0015 ."
    },
    {
        "type": "INV",
        "text": "okay ‡ thinking back , can you tell me a story about something important that happened to you in your life ? \u001594581_100021\u0015",
        "mor": "co|okay beg|beg part|think-PRESP n|back cm|cm mod|can pro:per|you",
        "gra": "1|0|BEG 2|1|BEGP 3|4|MOD 4|8|SUBJ 5|4|LP 6|8|AUX 7|8|SUBJ 8|0|ROOT",
        "wor": "okay \u001594581_95341\u0015 ‡ thinking \u001595461_95831\u0015 back \u001595831_96211\u0015 , can \u001596241_96391\u0015 you \u001596391_96491\u0015 tell \u001596491_96761\u0015 me \u001596761_96901\u0015 a \u001596901_96991\u0015 story \u001596991_97521\u0015 about \u001597521_97821\u0015 something \u001597821_98141\u0015 important \u001598141_98721\u0015 that \u001598721_98841\u0015 happened \u001598841_99271\u0015 to \u001599271_99411\u0015 you \u001599411_99531\u0015 in \u001599531_99681\u0015 your \u001599681_99831\u0015 life \u001599831_100021\u0015 ?"
    },
    {
        "type": "INV",
        "text": "it can be a happy or sad memory , from any time , from when you were a kid or more recently , just any important event . \u0015100362_107732\u0015",
        "mor": "pro:per|it mod|can cop|be det:art|a adj|happy coord|or adj|sad",
        "gra": "1|3|SUBJ 2|3|AUX 3|0|ROOT 4|5|DET 5|3|PRED 6|5|CONJ 7|8|MOD 8|6|COORD",
        "wor": "it \u0015100362_100482\u0015 can \u0015100482_100622\u0015 be \u0015100622_100782\u0015 a \u0015100782_100892\u0015 happy \u0015100892_101502\u0015 or \u0015101502_101672\u0015 sad \u0015101672_102032\u0015 memory \u0015102032_102422\u0015 , from \u0015102422_102622\u0015 any \u0015102622_102862\u0015 time \u0015102862_103302\u0015 , from \u0015103302_104012\u0015 when \u0015104012_104122\u0015 you \u0015104122_104222\u0015 were \u0015104222_104282\u0015 a \u0015104282_104382\u0015 kid \u0015104382_104622\u0015 or \u0015104622_104762\u0015 more \u0015104762_105022\u0015 recently \u0015105022_105652\u0015 , just \u0015106262_106452\u0015 any \u0015106452_106892\u0015 important \u0015106892_107442\u0015 event \u0015107442_107732\u0015 ."
    },
    {
        "type": "PAR",
        "text": "that's hard . \u0015110616_111466\u0015",
        "mor": "pro:dem|that~cop|be&3S adv|hard .",
        "gra": "1|2|SUBJ 2|0|ROOT 3|2|JCT 4|2|PUNCT",
        "wor": "that's \u0015110616_110956\u0015 hard \u0015110956_111466\u0015 ."
    },
    {
        "type": "PAR",
        "text": "I [/] <I need> [//] I think the saddest thing <that happened to &+m was> [//] that comes immediately is the sudden death of my father in nineteen eighty three . \u0015111518_122518\u0015",
        "mor": "pro:sub|I v|think det:art|the adj|sad-SP n|thing pro:rel|that",
        "gra": "1|2|SUBJ 2|0|ROOT 3|5|DET 4|5|MOD 5|9|SUBJ 6|7|LINK 7|5|CMOD 8|7|JCT",
        "wor": "I [/] \u0015111518_111748\u0015 <I \u0015113358_113598\u0015 need \u0015113598_113838\u0015> [//] I think the saddest thing <that happened to &+m was> [//] \u0015113838_117148\u0015 that \u0015117148_117968\u0015 comes \u0015117968_118258\u0015 immediately \u0015118258_118828\u0015 is \u0015118828_118988\u0015 the \u0015118988_119258\u0015 sudden \u0015119258_119688\u0015 death \u0015119688_119968\u0015 of \u0015119968_120148\u0015 my \u0015120148_120268\u0015 father \u0015120268_120958\u0015 in \u0015121288_121408\u0015 nineteen \u0015121408_121798\u0015 eighty \u0015121798_122008\u0015 three \u0015122008_122518\u0015 ."
    },
    {
        "type": "PAR",
        "text": "and &-uh that was very shocking and xxx +/. \u0015123266_126516\u0015",
        "mor": "coord|and pro:dem|that aux|be&PAST&13S adv|very part|shock-PRESP",
        "gra": "1|5|LINK 2|5|SUBJ 3|5|AUX 4|5|JCT 5|0|ROOT 6|5|CONJ 7|5|PUNCT",
        "wor": "and \u0015123266_123606\u0015 &-uh \u0015123606_123826\u0015 that \u0015123826_124246\u0015 was \u0015124246_124436\u0015 very \u0015124436_124616\u0015 shocking \u0015124616_125826\u0015 and \u0015126006_126516\u0015 xxx +/."
    },
    {
        "type": "INV",
        "text": "how does he die ? \u0015126007_126699\u0015",
        "mor": "pro:int|how mod|do&3S pro:sub|he v|die ?",
        "gra": "1|4|JCT 2|4|AUX 3|4|SUBJ 4|0|ROOT 5|4|PUNCT",
        "wor": "how \u0015125979_126149\u0015 does \u0015126149_126369\u0015 he \u0015126369_126409\u0015 die \u0015126409_126699\u0015 ?"
    },
    {
        "type": "PAR",
        "text": "he died of a massive heart attack , the first heart failure . \u0015127065_130145\u0015",
        "mor": "pro:sub|he v|die-PAST prep|of det:art|a adj|massive n|heart",
        "gra": "1|2|SUBJ 2|0|ROOT 3|2|JCT 4|7|DET 5|6|MOD 6|7|MOD 7|3|POBJ 8|2|LP",
        "wor": "he \u0015127065_127245\u0015 died \u0015127245_127505\u0015 of \u0015127505_127705\u0015 a \u0015127705_127805\u0015 massive \u0015127805_128275\u0015 heart \u0015128275_128665\u0015 attack \u0015128665_129025\u0015 , the \u0015129025_129095\u0015 first \u0015129095_129565\u0015 heart \u0015129565_129765\u0015 failure \u0015129765_130145\u0015 ."
    },
    {
        "type": "INV",
        "text": "yeah . \u0015130669_130930\u0015",
        "mor": "co|yeah .",
        "gra": "1|0|INCROOT 2|1|PUNCT",
        "wor": "yeah \u0015130670_130930\u0015 ."
    },
    {
        "type": "PAR",
        "text": "yeah ‡ and &-uh about five years ago my mother had a stroke . \u0015131228_135608\u0015",
        "mor": "co|yeah beg|beg coord|and prep|about det:num|five n|year-PL",
        "gra": "1|0|BEG 2|1|BEGP 3|5|LINK 4|5|JCT 5|6|QUANT 6|10|JCT 7|6|POSTMOD",
        "wor": "yeah \u0015131228_132448\u0015 ‡ and \u0015132878_133148\u0015 &-uh \u0015133148_133168\u0015 about \u0015133168_133468\u0015 five \u0015133468_133788\u0015 years \u0015133788_134028\u0015 ago \u0015134028_134228\u0015 my \u0015134228_134268\u0015 mother \u0015134268_134748\u0015 had \u0015134748_134938\u0015 a \u0015134938_134998\u0015 stroke \u0015134998_135608\u0015 ."
    },
    {
        "type": "PAR",
        "text": "so +... \u0015135678_136028\u0015",
        "mor": "co|so +...",
        "gra": "1|0|INCROOT 2|1|PUNCT",
        "wor": "so \u0015135678_136028\u0015 +..."
    },
    {
        "type": "INV",
        "text": "wow . \u0015136051_136711\u0015",
        "mor": "co|wow .",
        "gra": "1|0|INCROOT 2|1|PUNCT",
        "wor": "wow \u0015136051_136711\u0015 ."
    },
    {
        "type": "PAR",
        "text": "and my &+dau sister had a stroke the same year . \u0015136759_139449\u0015",
        "mor": "coord|and det:poss|my n|sister v|have&PAST det:art|a n|stroke",
        "gra": "1|4|LINK 2|3|DET 3|4|SUBJ 4|0|ROOT 5|6|DET 6|4|OBJ 7|9|DET 8|9|MOD",
        "wor": "and \u0015136759_137139\u0015 my \u0015137139_137199\u0015 &+dau \u0015137229_137449\u0015 sister \u0015137449_137899\u0015 had \u0015137899_138099\u0015 a \u0015138099_138159\u0015 stroke \u0015138159_138869\u0015 the \u0015138869_138959\u0015 same \u0015138959_139279\u0015 year \u0015139279_139449\u0015 ."
    },
    {
        "type": "PAR",
        "text": "they are getting better . \u0015140419_142039\u0015",
        "mor": "pro:sub|they aux|be&PRES part|get-PRESP adj|good&CP .",
        "gra": "1|3|SUBJ 2|3|AUX 3|0|ROOT 4|3|PRED 5|3|PUNCT",
        "wor": "they \u0015140419_140629\u0015 are \u0015140629_141209\u0015 getting \u0015141369_141669\u0015 better \u0015141669_142039\u0015 ."
    },
    {
        "type": "INV",
        "text": "that's good . \u0015142059_142589\u0015",
        "mor": "pro:dem|that~cop|be&3S adj|good .",
        "gra": "1|2|SUBJ 2|0|ROOT 3|2|PRED 4|2|PUNCT",
        "wor": "that's \u0015142059_142349\u0015 good \u0015142349_142589\u0015 ."
    },
    {
        "type": "PAR",
        "text": "but yeah I_mean sister is still recovering . \u0015142647_145837\u0015",
        "mor": "conj|but co|yeah co|I_mean n|sister aux|be&3S adv|still",
        "gra": "1|7|LINK 2|4|COM 3|4|COM 4|7|SUBJ 5|7|AUX 6|7|JCT 7|0|ROOT 8|7|PUNCT",
        "wor": "but \u0015142647_142847\u0015 yeah \u0015142847_142977\u0015 I_mean \u0015142977_144007\u0015 sister \u0015144217_144537\u0015 is \u0015144537_144727\u0015 still \u0015144727_145137\u0015 recovering \u0015145137_145837\u0015 ."
    },
    {
        "type": "PAR",
        "text": "it was very bad . \u0015146601_147931\u0015",
        "mor": "pro:per|it cop|be&PAST&13S adv|very adj|bad .",
        "gra": "1|2|SUBJ 2|0|ROOT 3|4|JCT 4|2|PRED 5|2|PUNCT",
        "wor": "it \u0015146601_146791\u0015 was \u0015146791_147111\u0015 very \u0015147111_147571\u0015 bad \u0015147651_147931\u0015 ."
    },
    {
        "type": "PAR",
        "text": "but &-uh my mother is doing okay . \u0015147947_151147\u0015",
        "mor": "conj|but det:poss|my n|mother aux|be&3S part|do-PRESP adj|okay .",
        "gra": "1|5|LINK 2|3|DET 3|5|SUBJ 4|5|AUX 5|0|ROOT 6|5|PRED 7|5|PUNCT",
        "wor": "but \u0015147947_148357\u0015 &-uh \u0015148357_148477\u0015 my \u0015148477_148667\u0015 mother \u0015148667_149327\u0015 is \u0015150027_150267\u0015 doing \u0015150267_150607\u0015 okay \u0015150607_151147\u0015 ."
    },
    {
        "type": "PAR",
        "text": "but she has some &-uh &-hm issues which are not that severe . \u0015151325_156915\u0015",
        "mor": "conj|but pro:sub|she v|have&3S qn|some n|issue-PL pro:rel|which",
        "gra": "1|3|LINK 2|3|SUBJ 3|0|ROOT 4|5|QUANT 5|3|OBJ 6|7|LINK 7|5|CMOD 8|7|NEG",
        "wor": "but \u0015151325_151615\u0015 she \u0015151615_151745\u0015 has \u0015151745_152115\u0015 some \u0015152115_152735\u0015 &-uh \u0015152765_153315\u0015 &-hm \u0015153685_154125\u0015 issues \u0015154215_154925\u0015 which \u0015154925_155335\u0015 are \u0015155795_155965\u0015 not \u0015155965_156245\u0015 that \u0015156245_156445\u0015 severe \u0015156445_156915\u0015 ."
    },
    {
        "type": "PAR",
        "text": "but [/] but they are both on [//] pretty much recovered . \u0015156960_161130\u0015",
        "mor": "conj|but pro:sub|they cop|be&PRES qn|both adv|pretty adv|much",
        "gra": "1|3|LINK 2|3|SUBJ 3|0|ROOT 4|7|QUANT 5|6|JCT 6|7|JCT 7|3|PRED 8|3|PUNCT",
        "wor": "but [/] \u0015156960_157430\u0015 but \u0015157460_157850\u0015 they \u0015157880_158170\u0015 are \u0015158200_158380\u0015 both \u0015158380_158930\u0015 on [//] \u0015158930_160020\u0015 pretty \u0015160330_160520\u0015 much \u0015160520_160800\u0015 recovered \u0015160800_161130\u0015 ."
    },
    {
        "type": "INV",
        "text": "that's good . \u0015161152_161852\u0015",
        "mor": "pro:dem|that~cop|be&3S adj|good .",
        "gra": "1|2|SUBJ 2|0|ROOT 3|2|PRED 4|2|PUNCT",
        "wor": "that's \u0015161152_161402\u0015 good \u0015161402_161852\u0015 ."
    },
    {
        "type": "PAR",
        "text": "+< so ‡ I [//] coming to the life turning events , I_mean those are the closest people . \u0015161403_166372\u0015",
        "mor": "co|so beg|beg part|come-PRESP prep|to det:art|the n|life",
        "gra": "1|0|BEG 2|1|BEGP 3|0|ROOT 4|3|JCT 5|6|DET 6|4|POBJ 7|3|XJCT 8|7|OBJ",
        "wor": "+< so \u0015161372_161572\u0015 ‡ I [//] \u0015161572_161852\u0015 coming \u0015162452_162782\u0015 to \u0015162782_162902\u0015 the \u0015162902_162932\u0015 life \u0015162932_163312\u0015 turning \u0015163312_163682\u0015 events \u0015163682_164082\u0015 , I_mean \u0015164082_164422\u0015 those \u0015164422_164652\u0015 are \u0015164652_164922\u0015 the \u0015164922_165152\u0015 closest \u0015165152_165662\u0015 people \u0015165662_166372\u0015 ."
    },
    {
        "type": "INV",
        "text": "right . \u0015166766_166976\u0015",
        "mor": "co|right .",
        "gra": "1|0|INCROOT 2|1|PUNCT",
        "wor": "right \u0015166766_166976\u0015 ."
    },
    {
        "type": "PAR",
        "text": "yeah ‡ and then the happy part is &-like you_know my kids born [//] being born . \u0015167310_173000\u0015",
        "mor": "co|yeah beg|beg coord|and adv:tem|then det:art|the adj|happy n|part",
        "gra": "1|0|BEG 2|1|BEGP 3|8|LINK 4|8|JCT 5|7|DET 6|7|MOD 7|8|SUBJ 8|0|ROOT",
        "wor": "yeah \u0015167310_167860\u0015 ‡ and \u0015167890_168230\u0015 then \u0015168230_168710\u0015 the \u0015168710_168730\u0015 happy \u0015168730_169560\u0015 part \u0015169560_169980\u0015 is \u0015169980_170390\u0015 &-like \u0015170390_170810\u0015 you_know \u0015170810_171260\u0015 my \u0015171260_171320\u0015 kids \u0015171320_171760\u0015 born [//] being born . \u0015171810_173000\u0015"
    },
    {
        "type": "INV",
        "text": "mhm . \u0015173021_173671\u0015",
        "mor": "co|mhm=yes .",
        "gra": "1|0|INCROOT 2|1|PUNCT",
        "wor": "mhm \u0015173021_173671\u0015 ."
    },
    {
        "type": "PAR",
        "text": "so ‡ that [/] that is xxx the times . \u0015173689_176789\u0015",
        "mor": "co|so beg|beg pro:dem|that cop|be&3S det:art|the n|time-PL .",
        "gra": "1|0|BEG 2|1|BEGP 3|4|SUBJ 4|0|ROOT 5|6|DET 6|4|PRED 7|4|PUNCT",
        "wor": "so \u0015173689_173899\u0015 ‡ that [/] \u0015173899_174429\u0015 that \u0015174429_174969\u0015 is \u0015174969_176199\u0015 xxx the \u0015176199_176269\u0015 times \u0015176269_176789\u0015 ."
    },
    {
        "type": "PAR",
        "text": "and getting married and +... \u0015176840_178380\u0015",
        "mor": "coord|and part|get-PRESP part|marry-PASTP coord|and +...",
        "gra": "1|2|LINK 2|0|ROOT 3|2|COMP 4|2|CONJ 5|2|PUNCT",
        "wor": "and \u0015176840_177310\u0015 getting \u0015177310_177620\u0015 married \u0015177620_178200\u0015 and \u0015178200_178380\u0015 +..."
    },
    {
        "type": "INV",
        "text": "&=laughs the good things . \u0015178816_179806\u0015",
        "mor": "det:art|the adj|good n|thing-PL .",
        "gra": "1|3|DET 2|3|MOD 3|0|INCROOT 4|3|PUNCT",
        "wor": "&=laughs the \u0015178816_179036\u0015 good \u0015179196_179426\u0015 things \u0015179426_179806\u0015 ."
    },
    {
        "type": "INV",
        "text": "there's good things . \u0015179851_180291\u0015",
        "mor": "pro:exist|there~cop|be&3S adj|good n|thing-PL .",
        "gra": "1|2|SUBJ 2|0|ROOT 3|4|MOD 4|2|PRED 5|2|PUNCT",
        "wor": "there's \u0015179851_179951\u0015 good \u0015179951_180161\u0015 things \u0015180161_180291\u0015 ."
    },
    {
        "type": "PAR",
        "text": "+< good things . \u0015180261_180461\u0015",
        "mor": "adj|good n|thing-PL .",
        "gra": "1|2|MOD 2|0|INCROOT 3|2|PUNCT",
        "wor": "+< good \u0015180261_180351\u0015 things \u0015180351_180461\u0015 ."
    },
    {
        "type": "PAR",
        "text": "good and bad . \u0015180702_181342\u0015",
        "mor": "adj|good coord|and adj|bad .",
        "gra": "1|0|INCROOT 2|1|CONJ 3|2|COORD 4|1|PUNCT",
        "wor": "good \u0015180702_180792\u0015 and \u0015180792_180892\u0015 bad \u0015180892_181342\u0015 ."
    },
    {
        "type": "INV",
        "text": "+< yeah . \u0015181640_181760\u0015",
        "mor": "co|yeah .",
        "gra": "1|0|INCROOT 2|1|PUNCT",
        "wor": "+< yeah \u0015181640_181760\u0015 ."
    },
    {
        "type": "PAR",
        "text": "+< so ‡ that's what I think life is made of &=laughs . \u0015181641_184794\u0015",
        "mor": "co|so beg|beg pro:dem|that~cop|be&3S pro:int|what pro:sub|I v|think",
        "gra": "1|0|BEG 2|1|BEGP 3|4|SUBJ 4|0|ROOT 5|7|LINK 6|7|SUBJ 7|4|CPRED",
        "wor": "+< so \u0015181444_181484\u0015 ‡ that's \u0015181484_181814\u0015 what \u0015181814_182044\u0015 I \u0015182044_182144\u0015 think \u0015182144_182394\u0015 life \u0015182394_182704\u0015 is \u0015182704_182804\u0015 made \u0015182804_182984\u0015 of \u0015182984_184794\u0015 &=laughs ."
    },
    {
        "type": "INV",
        "text": "I agree &=laughs . \u0015184841_186201\u0015",
        "mor": "pro:sub|I v|agree .",
        "gra": "1|2|SUBJ 2|0|ROOT 3|2|PUNCT",
        "wor": "I \u0015184841_186071\u0015 agree \u0015186101_186201\u0015 &=laughs ."
    },
    {
        "type": "INV",
        "text": "okay ‡ good . \u0015186333_187073\u0015",
        "mor": "co|okay beg|beg adj|good .",
        "gra": "1|0|BEG 2|1|BEGP 3|0|INCROOT 4|3|PUNCT",
        "wor": "okay \u0015186333_186693\u0015 ‡ good \u0015186693_187073\u0015 ."
    },
    {
        "type": "INV",
        "text": "okay . \u0015187640_187970\u0015",
        "mor": "co|okay .",
        "gra": "1|0|INCROOT 2|1|PUNCT",
        "wor": "okay \u0015187640_187970\u0015 ."
    },
    {
        "type": "INV",
        "text": "so ‡ now I'm gonna show you &-um a few pictures . \u0015188090_190450\u0015",
        "mor": "co|so beg|beg adv:tem|now pro:sub|I~aux|be&1S part|go&PRESP~inf|to",
        "gra": "1|0|BEG 2|1|BEGP 3|6|LINK 4|6|SUBJ 5|6|AUX 6|0|ROOT 7|8|INF 8|6|COMP",
        "wor": "so \u0015188090_188160\u0015 ‡ now \u0015188160_188380\u0015 I'm \u0015188380_188500\u0015 gonna \u0015188500_188680\u0015 show \u0015188680_188880\u0015 you \u0015188880_189270\u0015 &-um \u0015189270_189670\u0015 a \u0015189670_189710\u0015 few \u0015189710_189950\u0015 pictures \u0015189950_190450\u0015 ."
    },
    {
        "type": "PAR",
        "text": "and I just want you to look at them and tell me a story with a beginning a middle and an end . \u0015191322_195802\u0015",
        "mor": "coord|and pro:sub|I adv|just v|want pro:per|you inf|to v|look",
        "gra": "1|4|LINK 2|4|SUBJ 3|4|JCT 4|0|ROOT 5|7|SUBJ 6|7|INF 7|4|COMP 8|7|JCT",
        "wor": "and \u0015191322_191452\u0015 I \u0015191452_191542\u0015 just \u0015191542_191742\u0015 want \u0015191742_191882\u0015 you \u0015191882_191952\u0015 to \u0015191952_192032\u0015 look \u0015192032_192312\u0015 at \u0015192312_192452\u0015 them \u0015192452_192642\u0015 and \u0015192642_192902\u0015 tell \u0015192902_193142\u0015 me \u0015193142_193272\u0015 a \u0015193272_193332\u0015 story \u0015193332_193872\u0015 with \u0015193872_194022\u0015 a \u0015194022_194242\u0015 beginning \u0015194272_194742\u0015 a \u0015194742_194872\u0015 middle \u0015194872_195142\u0015 and \u0015195142_195302\u0015 an \u0015195302_195442\u0015 end \u0015195442_195802\u0015 ."
    },
    {
        "type": "PAR",
        "text": "oh ‡ I need to make a story by looking at the pictures ? [+ exc] \u0015196153_199173\u0015",
        "mor": "co|oh beg|beg pro:sub|I v|need inf|to v|make det:art|a n|story",
        "gra": "1|0|BEG 2|1|BEGP 3|4|SUBJ 4|0|ROOT 5|6|INF 6|4|COMP 7|8|DET 8|6|OBJ",
        "wor": "oh \u0015196153_196223\u0015 ‡ I \u0015196533_197033\u0015 need \u0015197033_197243\u0015 to \u0015197243_197383\u0015 make \u0015197383_197633\u0015 a \u0015197633_197703\u0015 story \u0015197703_198063\u0015 by \u0015198063_198253\u0015 looking \u0015198253_198523\u0015 at \u0015198523_198773\u0015 the \u0015198773_198783\u0015 pictures \u0015198783_199173\u0015 ? [+ exc]"
    },
    {
        "type": "INV",
        "text": "yep . \u0015199189_199609\u0015",
        "mor": "co|yep .",
        "gra": "1|0|INCROOT 2|1|PUNCT",
        "wor": "yep \u0015199189_199609\u0015 ."
    },
    {
        "type": "INV",
        "text": "yep ‡ with these four pictures . \u0015200063_201843\u0015",
        "mor": "co|yep beg|beg prep|with det:dem|these det:num|four n|picture-PL .",
        "gra": "1|0|BEG 2|1|BEGP 3|0|INCROOT 4|6|DET 5|6|QUANT 6|3|POBJ 7|3|PUNCT",
        "wor": "yep \u0015200063_200313\u0015 ‡ with \u0015200313_200453\u0015 these \u0015200453_200913\u0015 four \u0015200913_201193\u0015 pictures \u0015201193_201843\u0015 ."
    },
    {
        "type": "PAR",
        "text": "&+s &-like a boy's playing ball . \u0015201981_211761\u0015",
        "mor": "det:art|a n|boy~aux|be&3S part|play-PRESP n|ball .",
        "gra": "1|2|DET 2|4|SUBJ 3|4|AUX 4|0|ROOT 5|4|OBJ 6|4|PUNCT",
        "wor": "&+s \u0015201981_202011\u0015 &-like \u0015202061_202151\u0015 a \u0015202501_202811\u0015 boy's \u0015203151_203241\u0015 playing \u0015203381_209561\u0015 ball \u0015209611_211761\u0015 ."
    },
    {
        "type": "PAR",
        "text": "and then in front yard or &+back backyard of a house . \u0015212251_216981\u0015",
        "mor": "coord|and adv:tem|then prep|in n|front n|yard coord|or",
        "gra": "1|0|INCROOT 2|1|COORD 3|2|JCT 4|5|MOD 5|3|POBJ 6|3|CONJ 7|6|COORD",
        "wor": "and \u0015212251_212631\u0015 then \u0015212631_213271\u0015 in \u0015213271_213631\u0015 front \u0015213631_214811\u0015 yard \u0015214811_215181\u0015 or \u0015215181_215301\u0015 &+back \u0015215301_215531\u0015 backyard \u0015215671_216161\u0015 of \u0015216161_216341\u0015 a \u0015216341_216481\u0015 house \u0015216481_216981\u0015 ."
    },
    {
        "type": "PAR",
        "text": "and then the ball smashes the window . \u0015217031_219651\u0015",
        "mor": "coord|and adv:tem|then det:art|the n|ball v|smash-3S det:art|the",
        "gra": "1|5|LINK 2|5|JCT 3|4|DET 4|5|SUBJ 5|0|ROOT 6|7|DET 7|5|OBJ 8|5|PUNCT",
        "wor": "and \u0015217031_217231\u0015 then \u0015217231_217571\u0015 the \u0015217941_218091\u0015 ball \u0015218091_218361\u0015 smashes \u0015218361_218991\u0015 the \u0015218991_219051\u0015 window \u0015219051_219651\u0015 ."
    },
    {
        "type": "PAR",
        "text": "and it hits &-uh the &+l table lamp . \u0015219672_224562\u0015",
        "mor": "coord|and pro:per|it v|hit-3S det:art|the n|table n|lamp .",
        "gra": "1|3|LINK 2|3|SUBJ 3|0|ROOT 4|6|DET 5|6|MOD 6|3|OBJ 7|3|PUNCT",
        "wor": "and \u0015219672_220102\u0015 it \u0015220102_220282\u0015 hits \u0015220282_220782\u0015 &-uh \u0015221872_222912\u0015 the \u0015222912_223192\u0015 &+l \u0015223192_223272\u0015 table \u0015223272_223682\u0015 lamp \u0015223682_224562\u0015 ."
    },
    {
        "type": "PAR",
        "text": "and &-uh the man sitting next to him picks up the ball . \u0015225085_230405\u0015",
        "mor": "coord|and det:art|the n|man part|sit-PRESP adv|next prep|to",
        "gra": "1|8|LINK 2|3|DET 3|8|SUBJ 4|3|XMOD 5|4|JCT 6|4|JCT 7|6|POBJ 8|0|ROOT",
        "wor": "and \u0015225085_225785\u0015 &-uh \u0015225785_226325\u0015 the \u0015227155_227185\u0015 man \u0015227185_228025\u0015 sitting \u0015228025_228505\u0015 next \u0015228505_228875\u0015 to \u0015228875_229025\u0015 him \u0015229025_229265\u0015 picks \u0015229265_229525\u0015 up \u0015229525_229575\u0015 the \u0015229575_229655\u0015 ball \u0015229655_230405\u0015 ."
    },
    {
        "type": "PAR",
        "text": "and it seems he's not happy . \u0015230420_232580\u0015",
        "mor": "coord|and pro:per|it cop|seem-3S pro:sub|he~cop|be&3S neg|not",
        "gra": "1|3|LINK 2|3|SUBJ 3|0|ROOT 4|5|SUBJ 5|3|PRED 6|5|NEG 7|5|PRED 8|3|PUNCT",
        "wor": "and \u0015230420_230660\u0015 it \u0015230660_230830\u0015 seems \u0015230830_231600\u0015 he's \u0015231600_231820\u0015 not \u0015231820_232090\u0015 happy \u0015232090_232580\u0015 ."
    },
    {
        "type": "PAR",
        "text": "and he turns back and looks out <of the> [/] of the window . \u0015232597_236537\u0015",
        "mor": "coord|and pro:sub|he v|turn-3S adv|back coord|and n|look-PL adv|out",
        "gra": "1|3|LINK 2|3|SUBJ 3|0|ROOT 4|3|JCT 5|3|CONJ 6|5|COORD 7|6|NJCT 8|7|JCT",
        "wor": "and \u0015232597_233267\u0015 he \u0015233307_233317\u0015 turns \u0015233317_233637\u0015 back \u0015233637_234007\u0015 and \u0015234007_234257\u0015 looks \u0015234257_234757\u0015 out \u0015234757_234997\u0015 <of \u0015234997_235227\u0015 the \u0015235227_235307\u0015> [/] of the window . \u0015235427_236537\u0015"
    },
    {
        "type": "PAR",
        "text": "and I don't see his expression so I don't know if [/] if he's happy or sad . \u0015238555_242235\u0015",
        "mor": "coord|and pro:sub|I mod|do~neg|not v|see det:poss|his n|expression",
        "gra": "1|5|LINK 2|5|SUBJ 3|5|AUX 4|3|NEG 5|0|ROOT 6|7|DET 7|5|OBJ 8|12|LINK",
        "wor": "and \u0015238555_238855\u0015 I \u0015238855_238955\u0015 don't \u0015238955_239155\u0015 see \u0015239155_239315\u0015 his \u0015239315_239475\u0015 expression \u0015239475_240035\u0015 so \u0015240035_240225\u0015 I \u0015240225_240305\u0015 don't \u0015240305_240515\u0015 know \u0015240515_240675\u0015 if [/] \u0015240705_240935\u0015 if \u0015240935_241365\u0015 he's \u0015241365_241515\u0015 happy \u0015241515_241805\u0015 or \u0015241805_241935\u0015 sad \u0015241935_242235\u0015 ."
    },
    {
        "type": "INV",
        "text": "good &=laughs . \u0015243203_243453\u0015",
        "mor": "adj|good .",
        "gra": "1|0|INCROOT 2|1|PUNCT",
        "wor": "good \u0015243203_243453\u0015 &=laughs ."
    },
    {
        "type": "PAR",
        "text": "he must be unhappy . \u0015243652_244622\u0015",
        "mor": "pro:sub|he mod|must cop|be un#adj|happy .",
        "gra": "1|3|SUBJ 2|3|AUX 3|0|ROOT 4|3|PRED 5|3|PUNCT",
        "wor": "he \u0015243652_243752\u0015 must \u0015243752_244012\u0015 be \u0015244012_244102\u0015 unhappy \u0015244102_244622\u0015 ."
    },
    {
        "type": "INV",
        "text": "I would think so . \u0015244730_245700\u0015",
        "mor": "pro:sub|I mod|will&COND v|think co|so .",
        "gra": "1|3|SUBJ 2|3|AUX 3|0|ROOT 4|3|OBJ 5|3|PUNCT",
        "wor": "I \u0015244730_244940\u0015 would \u0015244940_245090\u0015 think \u0015245140_245340\u0015 so \u0015245340_245700\u0015 ."
    },
    {
        "type": "INV",
        "text": "okay ‡ &-um let's do this one . \u0015246482_249542\u0015",
        "mor": "co|okay beg|beg v|let~pro:obj|us v|do det:dem|this pro:indef|one .",
        "gra": "1|0|BEG 2|1|BEGP 3|0|ROOT 4|5|SUBJ 5|3|COMP 6|7|DET 7|5|OBJ 8|3|PUNCT",
        "wor": "okay \u0015246482_246872\u0015 ‡ &-um \u0015246872_246932\u0015 let's \u0015246932_247162\u0015 do \u0015247662_248272\u0015 this \u0015248272_249282\u0015 one \u0015249282_249542\u0015 ."
    },
    {
        "type": "INV",
        "text": "same thing with this picture . \u0015249594_250974\u0015",
        "mor": "adj|same n|thing prep|with det:dem|this n|picture .",
        "gra": "1|2|MOD 2|0|INCROOT 3|2|NJCT 4|5|DET 5|3|POBJ 6|2|PUNCT",
        "wor": "same \u0015249594_249924\u0015 thing \u0015249924_250164\u0015 with \u0015250324_250484\u0015 this \u0015250484_250654\u0015 picture \u0015250654_250974\u0015 ."
    },
    {
        "type": "PAR",
        "text": "(..) so ‡ it seems the story of a small boy and his mom . \u0015250995_263205\u0015",
        "mor": "co|so beg|beg pro:per|it cop|seem-3S det:art|the n|story prep|of",
        "gra": "1|0|BEG 2|1|BEGP 3|4|SUBJ 4|0|ROOT 5|6|DET 6|4|PRED 7|6|NJCT 8|10|DET",
        "wor": "(..) so \u0015250995_251035\u0015 ‡ it \u0015251035_251095\u0015 seems \u0015251095_251215\u0015 the \u0015251285_251915\u0015 story \u0015251915_252085\u0015 of \u0015252265_259715\u0015 a \u0015259715_260555\u0015 small \u0015260645_260915\u0015 boy \u0015260915_260975\u0015 and \u0015260975_261065\u0015 his \u0015261065_262085\u0015 mom \u0015262085_263205\u0015 ."
    },
    {
        "type": "PAR",
        "text": "and &-um I guess he's leaving for school . \u0015267713_271213\u0015",
        "mor": "coord|and pro:sub|I v|guess pro:sub|he~aux|be&3S part|leave-PRESP",
        "gra": "1|3|LINK 2|3|SUBJ 3|0|ROOT 4|6|SUBJ 5|6|AUX 6|3|COMP 7|6|JCT 8|7|POBJ",
        "wor": "and \u0015267713_268223\u0015 &-um \u0015268223_268643\u0015 I \u0015268643_268973\u0015 guess \u0015269443_269723\u0015 he's \u0015269723_269973\u0015 leaving \u0015269973_270313\u0015 for \u0015270313_270523\u0015 school \u0015270523_271213\u0015 ."
    },
    {
        "type": "PAR",
        "text": "and &-um &+hi think his mom is telling him to take an umbrella <but there> [//] because there may be a forecast for rain . \u0015272216_280326\u0015",
        "mor": "coord|and v|think det:poss|his n|mom aux|be&3S part|tell-PRESP",
        "gra": "1|2|LINK 2|0|ROOT 3|4|DET 4|6|SUBJ 5|6|AUX 6|2|COMP 7|6|OBJ 8|9|INF",
        "wor": "and \u0015272216_272866\u0015 &-um \u0015272896_273006\u0015 &+hi \u0015273006_273066\u0015 think \u0015273066_274466\u0015 his \u0015274466_274656\u0015 mom \u0015274656_275016\u0015 is \u0015275016_275186\u0015 telling \u0015275186_275666\u0015 him \u0015275666_275926\u0015 to \u0015275926_276116\u0015 take \u0015276116_276396\u0015 an \u0015276396_276486\u0015 umbrella \u0015276486_277146\u0015 <but \u0015277176_277346\u0015 there \u0015277346_277456\u0015> [//] because there may be a forecast for rain . \u0015277456_280326\u0015"
    },
    {
        "type": "PAR",
        "text": "he seems to be arguing that he doesn't need it . \u0015281235_283665\u0015",
        "mor": "pro:sub|he cop|seem-3S inf|to aux|be part|argue-PRESP comp|that",
        "gra": "1|2|SUBJ 2|0|ROOT 3|5|INF 4|5|AUX 5|2|XJCT 6|10|LINK 7|10|SUBJ 8|10|AUX",
        "wor": "he \u0015281235_281535\u0015 seems \u0015281535_281905\u0015 to \u0015281905_281975\u0015 be \u0015281975_282095\u0015 arguing \u0015282095_282805\u0015 that \u0015282805_282965\u0015 he \u0015282965_283035\u0015 doesn't \u0015283035_283365\u0015 need \u0015283365_283625\u0015 it \u0015283625_283665\u0015 ."
    },
    {
        "type": "PAR",
        "text": "and he steps out without the umbrella . \u0015283680_285770\u0015",
        "mor": "coord|and pro:sub|he n|step-PL adv|out prep|without det:art|the",
        "gra": "1|3|LINK 2|3|SUBJ 3|0|INCROOT 4|3|NJCT 5|4|JCT 6|7|DET 7|5|POBJ",
        "wor": "and \u0015283680_284110\u0015 he \u0015284110_284190\u0015 steps \u0015284190_284640\u0015 out \u0015284640_284800\u0015 without \u0015284800_285210\u0015 the \u0015285210_285230\u0015 umbrella \u0015285230_285770\u0015 ."
    },
    {
        "type": "PAR",
        "text": "and it starts to rain . \u0015285789_288129\u0015",
        "mor": "coord|and pro:per|it v|start-3S inf|to v|rain .",
        "gra": "1|3|LINK 2|3|SUBJ 3|0|ROOT 4|5|INF 5|3|COMP 6|3|PUNCT",
        "wor": "and \u0015285789_286439\u0015 it \u0015286439_286579\u0015 starts \u0015286579_287079\u0015 to \u0015287079_287349\u0015 rain \u0015287349_288129\u0015 ."
    },
    {
        "type": "PAR",
        "text": "and then keeps walking until <I guess> [//] he realizes , turns back , comes home . \u0015288152_294812\u0015",
        "mor": "coord|and adv:tem|then v|keep-3S part|walk-PRESP conj|until",
        "gra": "1|3|LINK 2|3|JCT 3|0|ROOT 4|3|OBJ 5|7|LINK 6|7|SUBJ 7|3|CJCT 8|7|LP",
        "wor": "and \u0015288152_288432\u0015 then \u0015288432_288732\u0015 keeps \u0015288732_289512\u0015 walking \u0015289512_290082\u0015 until \u0015290082_290462\u0015 <I \u0015290462_290602\u0015 guess \u0015290602_291082\u0015> [//] he realizes , turns back , comes home . \u0015291082_294812\u0015"
    },
    {
        "type": "PAR",
        "text": "and his mom <is not> [//] &+hap doesn't look happy . \u0015294827_297457\u0015",
        "mor": "coord|and det:poss|his n|mom mod|do&3S~neg|not v|look adj|happy .",
        "gra": "1|6|LINK 2|3|DET 3|6|SUBJ 4|6|AUX 5|4|NEG 6|0|ROOT 7|6|JCT 8|6|PUNCT",
        "wor": "and \u0015294827_295057\u0015 his \u0015295147_295357\u0015 mom \u0015295357_295567\u0015 <is \u0015295567_295757\u0015 not \u0015295757_296107\u0015> [//] &+hap doesn't look happy . \u0015296107_297457\u0015"
    },
    {
        "type": "PAR",
        "text": "and he takes the umbrella . \u0015298227_299787\u0015",
        "mor": "coord|and pro:sub|he v|take-3S det:art|the n|umbrella .",
        "gra": "1|3|LINK 2|3|SUBJ 3|0|ROOT 4|5|DET 5|3|OBJ 6|3|PUNCT",
        "wor": "and \u0015298227_298427\u0015 he \u0015298427_298507\u0015 takes \u0015298507_298777\u0015 the \u0015298777_298877\u0015 umbrella \u0015298877_299787\u0015 ."
    },
    {
        "type": "PAR",
        "text": "and he walks back , maybe to school . \u0015299803_302083\u0015",
        "mor": "coord|and pro:sub|he v|walk-3S adv|back cm|cm adv|maybe prep|to",
        "gra": "1|3|LINK 2|3|SUBJ 3|0|ROOT 4|3|JCT 5|3|LP 6|3|JCT 7|3|JCT 8|7|POBJ",
        "wor": "and \u0015299803_300083\u0015 he \u0015300083_300123\u0015 walks \u0015300123_300713\u0015 back \u0015300713_301283\u0015 , maybe \u0015301283_301573\u0015 to \u0015301573_301673\u0015 school \u0015301673_302083\u0015 ."
    },
    {
        "type": "INV",
        "text": "good [/] good . \u0015302796_303886\u0015",
        "mor": "adj|good .",
        "gra": "1|0|INCROOT 2|1|PUNCT",
        "wor": "good [/] \u0015302796_302946\u0015 good \u0015303676_303886\u0015 ."
    },
    {
        "type": "INV",
        "text": "okay ‡ one more . \u0015304771_306681\u0015",
        "mor": "co|okay beg|beg det:num|one adv|more .",
        "gra": "1|0|BEG 2|1|BEGP 3|0|INCROOT 4|3|JCT 5|3|PUNCT",
        "wor": "okay \u0015304771_305251\u0015 ‡ one \u0015306071_306281\u0015 more \u0015306281_306681\u0015 ."
    },
    {
        "type": "INV",
        "text": "same thing with this . \u0015307511_308481\u0015",
        "mor": "adj|same n|thing prep|with pro:dem|this .",
        "gra": "1|2|MOD 2|0|INCROOT 3|2|NJCT 4|3|POBJ 5|2|PUNCT",
        "wor": "same \u0015307511_307771\u0015 thing \u0015307771_307991\u0015 with \u0015307991_308161\u0015 this \u0015308161_308481\u0015 ."
    },
    {
        "type": "INV",
        "text": "what's happening here ? \u0015308503_309543\u0015",
        "mor": "pro:int|what~aux|be&3S part|happen-PRESP n|here ?",
        "gra": "1|3|SUBJ 2|3|AUX 3|0|ROOT 4|3|OBJ 5|3|PUNCT",
        "wor": "what's \u0015308503_308753\u0015 happening \u0015308753_309193\u0015 here \u0015309193_309543\u0015 ?"
    },
    {
        "type": "PAR",
        "text": "(..) &-hm seems like &-um maybe a small girl and her dad . \u0015318154_324884\u0015",
        "mor": "cop|seem-3S conj|like adv|maybe det:art|a adj|small n|girl",
        "gra": "1|0|ROOT 2|1|PRED 3|2|NJCT 4|6|DET 5|6|MOD 6|3|POBJ 7|6|CONJ 8|9|DET",
        "wor": "(..) &-hm \u0015318154_318504\u0015 seems \u0015318664_319264\u0015 like \u0015319264_319594\u0015 &-um \u0015319594_320154\u0015 maybe \u0015320814_321344\u0015 a \u0015321584_322094\u0015 small \u0015322234_322654\u0015 girl \u0015322654_323294\u0015 and \u0015323294_323844\u0015 her \u0015324204_324294\u0015 dad \u0015324294_324884\u0015 ."
    },
    {
        "type": "PAR",
        "text": "and they talk . \u0015324908_326648\u0015",
        "mor": "coord|and pro:sub|they v|talk .",
        "gra": "1|3|LINK 2|3|SUBJ 3|0|ROOT 4|3|PUNCT",
        "wor": "and \u0015324908_325338\u0015 they \u0015325998_326108\u0015 talk \u0015326108_326648\u0015 ."
    },
    {
        "type": "PAR",
        "text": "they came to a park or something for a stroll . \u0015327437_330497\u0015",
        "mor": "pro:sub|they v|come&PAST prep|to det:art|a n|park coord|or",
        "gra": "1|2|SUBJ 2|0|ROOT 3|2|JCT 4|5|DET 5|3|POBJ 6|2|CONJ 7|6|COORD 8|7|NJCT",
        "wor": "they \u0015327437_327507\u0015 came \u0015327507_327857\u0015 to \u0015327857_327997\u0015 a \u0015327997_328037\u0015 park \u0015328037_328597\u0015 or \u0015328597_328667\u0015 something \u0015328667_329477\u0015 for \u0015329477_329547\u0015 a \u0015329657_329847\u0015 stroll \u0015329847_330497\u0015 ."
    },
    {
        "type": "PAR",
        "text": "and &-uh for some reason the father climbed the tree . \u0015330516_335636\u0015",
        "mor": "coord|and prep|for qn|some n|reason det:art|the n|father",
        "gra": "1|7|LINK 2|7|JCT 3|4|QUANT 4|2|POBJ 5|6|DET 6|7|SUBJ 7|0|ROOT 8|9|DET",
        "wor": "and \u0015330516_331396\u0015 &-uh \u0015331396_331676\u0015 for \u0015331676_331896\u0015 some \u0015331896_332196\u0015 reason \u0015332196_332806\u0015 the \u0015333576_333676\u0015 father \u0015333676_334486\u0015 climbed \u0015334776_335076\u0015 the \u0015335076_335156\u0015 tree \u0015335156_335636\u0015 ."
    },
    {
        "type": "PAR",
        "text": "and seems he's having problem coming down . \u0015335656_338796\u0015",
        "mor": "coord|and cop|seem-3S pro:sub|he~aux|be&3S part|have-PRESP",
        "gra": "1|2|LINK 2|0|ROOT 3|5|SUBJ 4|5|AUX 5|2|CPRED 6|5|OBJ 7|6|XMOD 8|7|JCT",
        "wor": "and \u0015335656_336046\u0015 seems \u0015336046_336326\u0015 he's \u0015336326_336516\u0015 having \u0015336516_336776\u0015 problem \u0015336776_337826\u0015 coming \u0015337826_338346\u0015 down \u0015338346_338796\u0015 ."
    },
    {
        "type": "PAR",
        "text": "and then the [//] there's [/] there's a firetruck that comes to help with a ladder . \u0015339780_344580\u0015",
        "mor": "coord|and adv:tem|then pro:exist|there~cop|be&3S det:art|a",
        "gra": "1|4|LINK 2|4|JCT 3|4|SUBJ 4|0|ROOT 5|6|DET 6|4|PRED 7|8|LINK 8|6|CMOD",
        "wor": "and \u0015339780_340080\u0015 then \u0015340080_340530\u0015 the [//] \u0015340530_340930\u0015 there's [/] \u0015341190_341430\u0015 there's \u0015341430_341690\u0015 a \u0015341690_341780\u0015 firetruck \u0015341780_342440\u0015 that \u0015342440_342670\u0015 comes \u0015342670_343170\u0015 to \u0015343170_343380\u0015 help \u0015343380_343800\u0015 with \u0015343800_343920\u0015 a \u0015343920_343970\u0015 ladder \u0015343970_344580\u0015 ."
    },
    {
        "type": "PAR",
        "text": "although the [/] the dog and the girl are both trying at their end to do something . \u0015345254_351054\u0015",
        "mor": "conj|although det:art|the n|dog coord|and det:art|the n|girl",
        "gra": "1|0|INCROOT 2|3|DET 3|1|POBJ 4|3|CONJ 5|6|DET 6|4|COORD 7|3|CMOD",
        "wor": "although \u0015345254_345994\u0015 the [/] \u0015346684_346784\u0015 the \u0015346784_346824\u0015 dog \u0015346824_347184\u0015 and \u0015347184_347574\u0015 the \u0015347574_347584\u0015 girl \u0015347584_347724\u0015 are \u0015347724_348034\u0015 both \u0015348064_348284\u0015 trying \u0015348284_348904\u0015 at \u0015349394_349634\u0015 their \u0015349634_349824\u0015 end \u0015349824_350304\u0015 to \u0015350484_350544\u0015 do \u0015350544_350664\u0015 something \u0015350664_351054\u0015 ."
    },
    {
        "type": "INV",
        "text": "good . \u0015351540_351740\u0015",
        "mor": "adj|good .",
        "gra": "1|0|INCROOT 2|1|PUNCT",
        "wor": "good \u0015351540_351740\u0015 ."
    },
    {
        "type": "PAR",
        "text": "and xxx . [+ exc] \u0015351981_352821\u0015",
        "mor": "coord|and .",
        "gra": "1|0|INCROOT 2|1|PUNCT",
        "wor": "and \u0015351981_352821\u0015 xxx . [+ exc]"
    },
    {
        "type": "INV",
        "text": "yep ‡ very good . \u0015352976_353856\u0015",
        "mor": "co|yep beg|beg adv|very adj|good .",
        "gra": "1|0|BEG 2|1|BEGP 3|4|JCT 4|0|INCROOT 5|4|PUNCT",
        "wor": "yep \u0015352976_353286\u0015 ‡ very \u0015353286_353556\u0015 good \u0015353556_353856\u0015 ."
    },
    {
        "type": "INV",
        "text": "okay . \u0015354394_354514\u0015",
        "mor": "co|okay .",
        "gra": "1|0|INCROOT 2|1|PUNCT",
        "wor": "okay \u0015354394_354514\u0015 ."
    },
    {
        "type": "INV",
        "text": "let me grab &-uh my book . \u0015354908_356588\u0015",
        "mor": "v|let&ZERO pro:obj|me v|grab det:poss|my n|book .",
        "gra": "1|0|ROOT 2|3|SUBJ 3|1|COMP 4|5|DET 5|3|OBJ 6|1|PUNCT",
        "wor": "let \u0015354908_355028\u0015 me \u0015355028_355118\u0015 grab \u0015355118_356148\u0015 &-uh \u0015356178_356188\u0015 my \u0015356188_356248\u0015 book \u0015356248_356588\u0015 ."
    },
    {
        "type": "INV",
        "text": "have you heard of the story of Cinderella ? \u0015356834_358574\u0015",
        "mor": "aux|have pro:per|you v|hear&PAST prep|of det:art|the n|story",
        "gra": "1|3|LINK 2|3|SUBJ 3|0|ROOT 4|3|JCT 5|6|DET 6|4|POBJ 7|6|NJCT 8|7|POBJ",
        "wor": "have \u0015356834_356944\u0015 you \u0015356944_357044\u0015 heard \u0015357044_357224\u0015 of \u0015357224_357374\u0015 the \u0015357374_357434\u0015 story \u0015357434_357874\u0015 of \u0015357874_358024\u0015 Cinderella \u0015358024_358574\u0015 ?"
    },
    {
        "type": "PAR",
        "text": "yep . \u0015358873_359103\u0015",
        "mor": "co|yep .",
        "gra": "1|0|INCROOT 2|1|PUNCT",
        "wor": "yep \u0015358873_359103\u0015 ."
    },
    {
        "type": "INV",
        "text": "you've heard that . \u0015359184_359634\u0015",
        "mor": "pro:per|you~aux|have part|hear&PASTP comp|that .",
        "gra": "1|3|SUBJ 2|3|AUX 3|0|ROOT 4|3|OBJ 5|3|PUNCT",
        "wor": "you've \u0015359184_359354\u0015 heard \u0015359354_359504\u0015 that \u0015359504_359634\u0015 ."
    },
    {
        "type": "INV",
        "text": "okay ‡ let me just take a look xxx if I have it . \u0015359655_363805\u0015",
        "mor": "co|okay beg|beg v|let&ZERO pro:obj|me adv|just v|take det:art|a",
        "gra": "1|0|BEG 2|1|BEGP 3|0|ROOT 4|3|OBJ 5|6|JCT 6|3|COMP 7|8|DET 8|6|OBJ",
        "wor": "okay \u0015359655_359965\u0015 ‡ let \u0015360705_360855\u0015 me \u0015360855_361005\u0015 just \u0015361005_361425\u0015 take \u0015361455_361715\u0015 a \u0015361715_361755\u0015 look \u0015361755_362025\u0015 xxx if \u0015362025_362925\u0015 I \u0015362925_362985\u0015 have \u0015362985_363705\u0015 it \u0015363735_363805\u0015 ."
    },
    {
        "type": "INV",
        "text": "here we go . \u0015365055_365335\u0015",
        "mor": "adv|here pro:sub|we v|go .",
        "gra": "1|3|JCT 2|3|SUBJ 3|0|ROOT 4|3|PUNCT",
        "wor": "here \u0015365055_365265\u0015 we \u0015365265_365275\u0015 go \u0015365275_365335\u0015 ."
    },
    {
        "type": "INV",
        "text": "okay . \u0015366353_366693\u0015",
        "mor": "co|okay .",
        "gra": "1|0|INCROOT 2|1|PUNCT",
        "wor": "okay \u0015366353_366693\u0015 ."
    },
    {
        "type": "INV",
        "text": "&-um so ‡ this is just a picture book it has all of the events in the story of Cinderella . \u0015367966_372336\u0015",
        "mor": "co|so beg|beg pro:dem|this cop|be&3S adv|just det:art|a n|picture",
        "gra": "1|0|BEG 2|1|BEGP 3|4|SUBJ 4|0|ROOT 5|8|JCT 6|8|DET 7|8|MOD 8|4|PRED",
        "wor": "&-um \u0015367966_368036\u0015 so \u0015368036_368096\u0015 ‡ this \u0015368096_368386\u0015 is \u0015368386_368596\u0015 just \u0015368596_368816\u0015 a \u0015368816_368866\u0015 picture \u0015368866_369236\u0015 book \u0015369236_369446\u0015 it \u0015369446_369656\u0015 has \u0015369656_370136\u0015 all \u0015370256_370416\u0015 of \u0015370416_370566\u0015 the \u0015370566_370706\u0015 events \u0015370706_371226\u0015 in \u0015371226_371396\u0015 the \u0015371396_371476\u0015 story \u0015371476_371756\u0015 of \u0015371756_371846\u0015 Cinderella \u0015371846_372336\u0015 ."
    },
    {
        "type": "INV",
        "text": "you can take a look at it just to refresh your memory &-uh for a minute or two . \u0015372359_376649\u0015",
        "mor": "pro:per|you mod|can v|take det:art|a v|look prep|at pro:per|it",
        "gra": "1|3|SUBJ 2|3|AUX 3|0|ROOT 4|5|DET 5|3|OBJ 6|5|JCT 7|6|POBJ 8|10|JCT",
        "wor": "you \u0015372359_372529\u0015 can \u0015372529_372659\u0015 take \u0015372659_372869\u0015 a \u0015372869_372939\u0015 look \u0015372939_373169\u0015 at \u0015373169_373329\u0015 it \u0015373329_373459\u0015 just \u0015373459_373659\u0015 to \u0015373659_373819\u0015 refresh \u0015373849_374289\u0015 your \u0015374289_374379\u0015 memory \u0015374379_374919\u0015 &-uh \u0015375449_375709\u0015 for \u0015375709_375949\u0015 a \u0015375949_375999\u0015 minute \u0015375999_376309\u0015 or \u0015376309_376449\u0015 two \u0015376449_376649\u0015 ."
    },
    {
        "type": "INV",
        "text": "and then after you're done looking, close the book . \u0015376671_378881\u0015",
        "mor": "coord|and adv:tem|then conj|after pro:per|you~aux|be&PRES",
        "gra": "1|6|LINK 2|3|JCT 3|6|LINK 4|6|SUBJ 5|6|AUX 6|0|ROOT 7|6|XJCT 8|7|LP",
        "wor": "and \u0015376671_376951\u0015 then \u0015376951_377091\u0015 after \u0015377091_377491\u0015 you're \u0015377491_377691\u0015 done \u0015377691_377911\u0015 looking, \u0015377911_378271\u0015 close \u0015378271_378621\u0015 the \u0015378621_378741\u0015 book \u0015378741_378881\u0015 ."
    },
    {
        "type": "INV",
        "text": "and then I want you to retell the story to me . \u0015379101_381741\u0015",
        "mor": "coord|and adv:tem|then pro:sub|I v|want pro:per|you inf|to",
        "gra": "1|4|LINK 2|4|JCT 3|4|SUBJ 4|0|ROOT 5|4|OBJ 6|7|INF 7|5|COMP 8|9|DET",
        "wor": "and \u0015379101_379241\u0015 then \u0015379241_379361\u0015 I \u0015379361_379421\u0015 want \u0015379421_379631\u0015 you \u0015379631_379721\u0015 to \u0015379721_379871\u0015 retell \u0015379871_380341\u0015 the \u0015380341_380441\u0015 story \u0015380441_380791\u0015 to \u0015381431_381581\u0015 me \u0015381581_381741\u0015 ."
    },
    {
        "type": "PAR",
        "text": "www .",
        "mor": "",
        "gra": "",
        "wor": "www ."
    },
    {
        "type": "PAR",
        "text": "&-hm well ‡ I don't know if I can put it coherently . \u0015466088_469268\u0015",
        "mor": "co|well beg|beg pro:sub|I mod|do~neg|not v|know comp|if pro:sub|I",
        "gra": "1|0|BEG 2|1|BEGP 3|6|SUBJ 4|6|AUX 5|4|NEG 6|0|ROOT 7|10|LINK 8|10|SUBJ",
        "wor": "&-hm \u0015466088_466328\u0015 well \u0015466328_466618\u0015 ‡ I \u0015466618_466638\u0015 don't \u0015466638_467108\u0015 know \u0015467368_467448\u0015 if \u0015467488_467808\u0015 I \u0015467808_467898\u0015 can \u0015467898_468108\u0015 put \u0015468108_468358\u0015 it \u0015468358_468538\u0015 coherently \u0015468538_469268\u0015 ."
    },
    {
        "type": "PAR",
        "text": "but [//] &-um so ‡ I'm supposed to close the book ? \u0015469283_473453\u0015",
        "mor": "co|so beg|beg pro:sub|I~aux|be&1S part|suppose-PASTP inf|to v|close",
        "gra": "1|0|BEG 2|1|BEGP 3|5|SUBJ 4|5|AUX 5|0|ROOT 6|7|INF 7|5|COMP 8|9|DET",
        "wor": "but [//] \u0015469283_469693\u0015 &-um \u0015469693_470103\u0015 so \u0015470143_470503\u0015 ‡ I'm \u0015472263_472423\u0015 supposed \u0015472423_472773\u0015 to \u0015472773_472843\u0015 close \u0015472843_473163\u0015 the \u0015473163_473173\u0015 book \u0015473173_473453\u0015 ?"
    },
    {
        "type": "INV",
        "text": "yep ‡ and I'll take that . \u0015473590_474820\u0015",
        "mor": "co|yep beg|beg coord|and pro:sub|I~mod|will v|take pro:dem|that .",
        "gra": "1|0|BEG 2|1|BEGP 3|6|LINK 4|6|SUBJ 5|6|AUX 6|0|ROOT 7|6|OBJ 8|6|PUNCT",
        "wor": "yep \u0015473590_474020\u0015 ‡ and \u0015474020_474200\u0015 I'll \u0015474200_474350\u0015 take \u0015474350_474600\u0015 that \u0015474600_474820\u0015 ."
    },
    {
        "type": "INV",
        "text": "and then as best as you can . \u0015475049_476569\u0015",
        "mor": "coord|and adv:tem|then adv|as v|best conj|as pro:per|you mod|can .",
        "gra": "1|4|LINK 2|4|JCT 3|4|COORD 4|0|ROOT 5|7|COORD 6|7|SUBJ 7|4|ENUM",
        "wor": "and \u0015475049_475169\u0015 then \u0015475169_475509\u0015 as \u0015475599_475799\u0015 best \u0015475799_476079\u0015 as \u0015476079_476219\u0015 you \u0015476219_476319\u0015 can \u0015476319_476569\u0015 ."
    },
    {
        "type": "PAR",
        "text": "yeah . [+ exc] \u0015476846_477096\u0015",
        "mor": "co|yeah .",
        "gra": "1|0|INCROOT 2|1|PUNCT",
        "wor": "yeah \u0015476846_477096\u0015 . [+ exc]"
    },
    {
        "type": "PAR",
        "text": "so ‡ it's the story of the Cinderella &-um (..) who lives with her <I think> [//] stepmom and her stepsisters . \u0015477145_485915\u0015",
        "mor": "co|so beg|beg pro:per|it~cop|be&3S det:art|the n|story prep|of",
        "gra": "1|0|BEG 2|1|BEGP 3|4|SUBJ 4|0|ROOT 5|6|DET 6|4|PRED 7|6|NJCT 8|9|DET",
        "wor": "so \u0015477145_477345\u0015 ‡ it's \u0015477345_477455\u0015 the \u0015477455_477675\u0015 story \u0015477675_478015\u0015 of \u0015478015_478145\u0015 the \u0015478145_478235\u0015 Cinderella \u0015478235_479435\u0015 &-um \u0015479435_479885\u0015 (..) who \u0015481825_481895\u0015 lives \u0015481895_482275\u0015 with \u0015482275_482605\u0015 her \u0015482605_482955\u0015 <I \u0015482955_483075\u0015 think \u0015483075_483325\u0015> [//] stepmom and her stepsisters . \u0015483325_485915\u0015"
    },
    {
        "type": "PAR",
        "text": "<and then the> [//] and &-uh she's not treated well by her stepmom . \u0015486002_493372\u0015",
        "mor": "coord|and pro:sub|she~aux|be&3S neg|not part|treat-PASTP n|well",
        "gra": "1|5|LINK 2|5|SUBJ 3|5|AUX 4|3|NEG 5|0|ROOT 6|5|OBJ 7|5|JCT 8|9|DET",
        "wor": "<and \u0015486002_486952\u0015 then \u0015486952_487332\u0015 the \u0015488162_489522\u0015> [//] and &-uh she's not treated well by her stepmom . \u0015489522_493372\u0015"
    },
    {
        "type": "PAR",
        "text": "and the stepsisters don't treat her well either . \u0015493395_497755\u0015",
        "mor": "coord|and det:art|the step#n|sister-PL mod|do~neg|not v|treat",
        "gra": "1|6|LINK 2|3|DET 3|6|SUBJ 4|6|AUX 5|4|NEG 6|0|ROOT 7|8|DET 8|6|OBJ",
        "wor": "and \u0015493395_494125\u0015 the \u0015494125_494735\u0015 stepsisters \u0015494735_496075\u0015 don't \u0015496135_496345\u0015 treat \u0015496345_496635\u0015 her \u0015496635_496795\u0015 well \u0015496795_497225\u0015 either \u0015497225_497755\u0015 ."
    },
    {
        "type": "PAR",
        "text": "she's supposed to do all her household chores . \u0015498186_501266\u0015",
        "mor": "pro:sub|she~aux|be&3S part|suppose-PASTP inf|to v|do qn|all",
        "gra": "1|3|SUBJ 2|3|AUX 3|0|ROOT 4|5|INF 5|3|COMP 6|9|QUANT 7|9|DET 8|9|MOD",
        "wor": "she's \u0015498186_498426\u0015 supposed \u0015498426_499036\u0015 to \u0015499036_499116\u0015 do \u0015499116_499236\u0015 all \u0015499236_499416\u0015 her \u0015499416_499706\u0015 household \u0015499706_500626\u0015 chores \u0015500626_501266\u0015 ."
    },
    {
        "type": "PAR",
        "text": "and [/] &-um and she &+s seems she lives in kind_of &-um a den where [//] with animals . \u0015502059_510439\u0015",
        "mor": "coord|and pro:sub|she cop|seem-3S pro:sub|she n|life-PL adv|in",
        "gra": "1|3|LINK 2|3|SUBJ 3|0|ROOT 4|3|PRED 5|4|OBJ 6|5|NJCT 7|5|NJCT 8|9|DET",
        "wor": "and [/] \u0015502059_502369\u0015 &-um \u0015502369_503009\u0015 and \u0015503769_504239\u0015 she \u0015504239_504379\u0015 &+s \u0015504379_504819\u0015 seems \u0015504949_505449\u0015 she \u0015505449_505509\u0015 lives \u0015505509_506179\u0015 in \u0015506179_506359\u0015 kind_of \u0015506359_507539\u0015 &-um \u0015507539_507609\u0015 a \u0015507609_507659\u0015 den \u0015507659_508339\u0015 where [//] \u0015508339_508749\u0015 with \u0015509289_509639\u0015 animals \u0015509639_510439\u0015 ."
    },
    {
        "type": "PAR",
        "text": "and then there's an invitation for a party where <she's in> [//] &-like she doesn't get to go . \u0015510531_517981\u0015",
        "mor": "coord|and adv:tem|then pro:exist|there~cop|be&3S det:art|a",
        "gra": "1|4|LINK 2|4|JCT 3|4|SUBJ 4|0|ROOT 5|6|DET 6|4|PRED 7|6|NJCT 8|9|DET",
        "wor": "and \u0015510531_510771\u0015 then \u0015510771_511061\u0015 there's \u0015511531_511721\u0015 an \u0015511721_511841\u0015 invitation \u0015511841_512691\u0015 for \u0015512691_512861\u0015 a \u0015512861_512921\u0015 party \u0015512921_513721\u0015 where \u0015513721_514251\u0015 <she's \u0015515131_515581\u0015 in \u0015515581_515861\u0015> [//] &-like she doesn't get to go . \u0015515911_517981\u0015"
    },
    {
        "type": "PAR",
        "text": "and her sisters and all go . \u0015518005_520475\u0015",
        "mor": "coord|and det:poss|her n|sister-PL coord|and post|all v|go .",
        "gra": "1|0|INCROOT 2|3|DET 3|1|COORD 4|3|CONJ 5|6|SUBJ 6|4|COORD 7|1|PUNCT",
        "wor": "and \u0015518005_518425\u0015 her \u0015518425_518595\u0015 sisters \u0015518595_519535\u0015 and \u0015519535_519785\u0015 all \u0015519785_520065\u0015 go \u0015520095_520475\u0015 ."
    },
    {
        "type": "PAR",
        "text": "and &+th she's locked into [//] in the house . \u0015520490_522580\u0015",
        "mor": "coord|and pro:sub|she~aux|be&3S part|lock-PASTP prep|in det:art|the",
        "gra": "1|4|LINK 2|4|SUBJ 3|4|AUX 4|0|ROOT 5|4|JCT 6|7|DET 7|5|POBJ 8|4|PUNCT",
        "wor": "and \u0015520490_520620\u0015 &+th \u0015520620_520720\u0015 she's \u0015520720_521110\u0015 locked \u0015521110_521430\u0015 into [//] \u0015521430_521750\u0015 in \u0015521750_521870\u0015 the \u0015521870_521890\u0015 house \u0015521890_522580\u0015 ."
    },
    {
        "type": "PAR",
        "text": "I can't recall how [/] how she ends up being there because she wears this &-um magical shoe or something that she wears . \u0015523232_532522\u0015",
        "mor": "pro:sub|I mod|can~neg|not v|recall pro:int|how pro:sub|she v|end-3S",
        "gra": "1|4|SUBJ 2|4|AUX 3|2|NEG 4|0|ROOT 5|7|JCT 6|7|SUBJ 7|4|COMP 8|7|JCT",
        "wor": "I \u0015523232_523312\u0015 can't \u0015523312_523672\u0015 recall \u0015523672_524122\u0015 how [/] \u0015524122_524662\u0015 how \u0015525622_525742\u0015 she \u0015525742_525902\u0015 ends \u0015526712_527002\u0015 up \u0015527002_527162\u0015 being \u0015527162_527432\u0015 there \u0015527432_527642\u0015 because \u0015527642_528082\u0015 she \u0015528082_528132\u0015 wears \u0015528132_528672\u0015 this \u0015528672_529192\u0015 &-um \u0015529192_529822\u0015 magical \u0015530062_530582\u0015 shoe \u0015530582_531012\u0015 or \u0015531012_531192\u0015 something \u0015531192_531762\u0015 that \u0015531762_531962\u0015 she \u0015531962_532062\u0015 wears \u0015532062_532522\u0015 ."
    },
    {
        "type": "PAR",
        "text": "and she turns into a princess . \u0015532579_534039\u0015",
        "mor": "coord|and pro:sub|she v|turn-3S prep|into det:art|a n|princess .",
        "gra": "1|3|LINK 2|3|SUBJ 3|0|ROOT 4|3|JCT 5|6|DET 6|4|POBJ 7|3|PUNCT",
        "wor": "and \u0015532579_532659\u0015 she \u0015532659_532669\u0015 turns \u0015532669_533099\u0015 into \u0015533099_533319\u0015 a \u0015533319_533349\u0015 princess \u0015533349_534039\u0015 ."
    },
    {
        "type": "PAR",
        "text": "and then <in a> [//] there's a carriage in which she goes to the party where she meets this prince . \u0015534149_539899\u0015",
        "mor": "coord|and adv:tem|then pro:exist|there~cop|be&3S det:art|a",
        "gra": "1|4|LINK 2|4|JCT 3|4|SUBJ 4|0|ROOT 5|6|DET 6|4|PRED 7|6|NJCT 8|7|POBJ",
        "wor": "and \u0015534149_534329\u0015 then \u0015534329_534499\u0015 <in \u0015535019_535209\u0015 a \u0015535209_535569\u0015> [//] there's a carriage in which she goes to the party where she meets this prince . \u0015536059_539899\u0015"
    },
    {
        "type": "PAR",
        "text": "and &-um they like each other , dance . \u0015540022_543332\u0015",
        "mor": "coord|and pro:sub|they v|like qn|each qn|other cm|cm n|dance .",
        "gra": "1|3|LINK 2|3|SUBJ 3|0|ROOT 4|5|QUANT 5|7|QUANT 6|5|LP 7|3|OBJ 8|3|PUNCT",
        "wor": "and \u0015540022_540362\u0015 &-um \u0015540362_540602\u0015 they \u0015541212_541792\u0015 like \u0015541792_542312\u0015 each \u0015542312_542452\u0015 other \u0015542452_542712\u0015 , dance \u0015542712_543332\u0015 ."
    },
    {
        "type": "PAR",
        "text": "and she has a great time . \u0015543399_544939\u0015",
        "mor": "coord|and pro:sub|she v|have&3S det:art|a adj|great n|time .",
        "gra": "1|3|LINK 2|3|SUBJ 3|0|ROOT 4|6|DET 5|6|MOD 6|3|OBJ 7|3|PUNCT",
        "wor": "and \u0015543399_543559\u0015 she \u0015543559_543619\u0015 has \u0015543619_543899\u0015 a \u0015543899_544049\u0015 great \u0015544079_544389\u0015 time \u0015544389_544939\u0015 ."
    },
    {
        "type": "PAR",
        "text": "and I don't know who tells her . \u0015545585_547325\u0015",
        "mor": "coord|and pro:sub|I mod|do~neg|not v|know pro:int|who v|tell-3S",
        "gra": "1|5|LINK 2|5|SUBJ 3|5|AUX 4|3|NEG 5|0|ROOT 6|7|LINK 7|5|COMP 8|7|OBJ",
        "wor": "and \u0015545585_545815\u0015 I \u0015545815_546015\u0015 don't \u0015546235_546365\u0015 know \u0015546365_546475\u0015 who \u0015546475_546645\u0015 tells \u0015546645_547095\u0015 her \u0015547095_547325\u0015 ."
    },
    {
        "type": "PAR",
        "text": "and then once the clock strikes twelve or something she's supposed to turn [//] go back home . \u0015547345_554225\u0015",
        "mor": "coord|and adv:tem|then adv:tem|once det:art|the n|clock v|strike-3S",
        "gra": "1|3|LINK 2|3|JCT 3|6|LINK 4|5|DET 5|6|SUBJ 6|0|ROOT 7|6|OBJ 8|7|CONJ",
        "wor": "and \u0015547345_547515\u0015 then \u0015547515_547735\u0015 once \u0015547735_548055\u0015 the \u0015548055_548325\u0015 clock \u0015548325_548905\u0015 strikes \u0015548905_549535\u0015 twelve \u0015549535_549915\u0015 or \u0015549915_549985\u0015 something \u0015549985_550665\u0015 she's \u0015551155_551385\u0015 supposed \u0015551385_551825\u0015 to \u0015551825_551915\u0015 turn [//] \u0015551915_552555\u0015 go \u0015552665_552815\u0015 back \u0015552815_553245\u0015 home \u0015553245_554225\u0015 ."
    },
    {
        "type": "PAR",
        "text": "and then in a hurry to rush back home she drops one of her shoe . \u0015554319_559359\u0015",
        "mor": "coord|and adv:tem|then prep|in det:art|a n|hurry prep|to n|rush",
        "gra": "1|8|LINK 2|8|JCT 3|8|JCT 4|5|DET 5|3|POBJ 6|8|JCT 7|6|POBJ 8|9|JCT",
        "wor": "and \u0015554319_554459\u0015 then \u0015554459_554709\u0015 in \u0015555009_555099\u0015 a \u0015555099_555249\u0015 hurry \u0015555249_555469\u0015 to \u0015555469_555629\u0015 rush \u0015555809_556069\u0015 back \u0015556069_556359\u0015 home \u0015556359_556709\u0015 she \u0015556709_556909\u0015 drops \u0015557889_558259\u0015 one \u0015558259_558409\u0015 of \u0015558409_558569\u0015 her \u0015558569_558679\u0015 shoe \u0015558679_559359\u0015 ."
    },
    {
        "type": "PAR",
        "text": "&-um and then when she reaches home she realizes that . \u0015559509_565209\u0015",
        "mor": "coord|and adv:tem|then conj|when pro:sub|she v|reach-3S adv|home",
        "gra": "1|8|LINK 2|8|JCT 3|5|LINK 4|5|SUBJ 5|8|CJCT 6|5|JCT 7|8|SUBJ 8|0|ROOT",
        "wor": "&-um \u0015559509_560089\u0015 and \u0015560159_560529\u0015 then \u0015560529_561149\u0015 when \u0015561149_561299\u0015 she \u0015561299_561389\u0015 reaches \u0015561389_561899\u0015 home \u0015561899_562489\u0015 she \u0015563599_563719\u0015 realizes \u0015563719_564469\u0015 that \u0015564469_565209\u0015 ."
    },
    {
        "type": "PAR",
        "text": "and this prince comes and gives her the shoe . \u0015565231_568001\u0015",
        "mor": "coord|and det:dem|this n|prince v|come-3S coord|and v|give-3S",
        "gra": "1|4|LINK 2|3|DET 3|4|SUBJ 4|0|ROOT 5|4|CONJ 6|5|COORD 7|6|OBJ2 8|9|DET",
        "wor": "and \u0015565231_565401\u0015 this \u0015565401_565541\u0015 prince \u0015565541_565891\u0015 comes \u0015565891_566651\u0015 and \u0015566651_566951\u0015 gives \u0015567081_567371\u0015 her \u0015567371_567481\u0015 the \u0015567481_567621\u0015 shoe \u0015567621_568001\u0015 ."
    },
    {
        "type": "PAR",
        "text": "and they get married . \u0015568021_570021\u0015",
        "mor": "coord|and pro:sub|they aux|get part|marry-PASTP .",
        "gra": "1|4|LINK 2|4|SUBJ 3|4|AUX 4|0|ROOT 5|4|PUNCT",
        "wor": "and \u0015568021_568281\u0015 they \u0015568901_569471\u0015 get \u0015569471_569781\u0015 married \u0015569781_570021\u0015 ."
    },
    {
        "type": "PAR",
        "text": "and then they live happily hereafter &=laughs . \u0015570267_572387\u0015",
        "mor": "coord|and adv:tem|then pro:sub|they v|live adv|happy&dadj-LY",
        "gra": "1|4|LINK 2|4|JCT 3|4|SUBJ 4|0|ROOT 5|4|JCT 6|4|JCT 7|4|PUNCT",
        "wor": "and \u0015570267_570487\u0015 then \u0015570487_570657\u0015 they \u0015570657_570747\u0015 live \u0015570747_571007\u0015 happily \u0015571007_571437\u0015 hereafter \u0015571437_572387\u0015 &=laughs ."
    },
    {
        "type": "INV",
        "text": "good ‡ that was pretty good . \u0015572793_574273\u0015",
        "mor": "adj|good beg|beg pro:dem|that cop|be&PAST&13S adv|pretty adj|good .",
        "gra": "1|0|BEG 2|1|BEGP 3|4|SUBJ 4|0|ROOT 5|6|JCT 6|4|PRED 7|4|PUNCT",
        "wor": "good \u0015572793_573253\u0015 ‡ that \u0015573253_573373\u0015 was \u0015573483_573753\u0015 pretty \u0015573753_574033\u0015 good \u0015574033_574273\u0015 ."
    },
    {
        "type": "INV",
        "text": "alright ‡ I think we just have one more question . \u0015576577_580307\u0015",
        "mor": "co|alright beg|beg pro:sub|I v|think pro:sub|we adv|just v|have",
        "gra": "1|0|BEG 2|1|BEGP 3|4|SUBJ 4|0|ROOT 5|7|SUBJ 6|7|JCT 7|4|COMP 8|7|OBJ",
        "wor": "alright \u0015576577_576997\u0015 ‡ I \u0015576997_577117\u0015 think \u0015577207_578337\u0015 we \u0015578337_578457\u0015 just \u0015578457_578777\u0015 have \u0015578777_579297\u0015 one \u0015579297_579527\u0015 more \u0015579527_579647\u0015 question \u0015579647_580307\u0015 ."
    },
    {
        "type": "INV",
        "text": "&-um okay . \u0015581204_584464\u0015",
        "mor": "co|okay .",
        "gra": "1|0|INCROOT 2|1|PUNCT",
        "wor": "&-um \u0015581204_581944\u0015 okay \u0015584184_584464\u0015 ."
    },
    {
        "type": "INV",
        "text": "so ‡ this one's a little bit different . \u0015584577_585817\u0015",
        "mor": "co|so beg|beg pro:dem|this pro:indef|one~cop|be&3S det:art|a",
        "gra": "1|0|BEG 2|1|BEGP 3|4|DET 4|5|SUBJ 5|0|ROOT 6|8|DET 7|8|MOD 8|5|PRED",
        "wor": "so \u0015584577_584617\u0015 ‡ this \u0015584617_584827\u0015 one's \u0015584827_584997\u0015 a \u0015584997_585067\u0015 little \u0015585067_585317\u0015 bit \u0015585317_585537\u0015 different \u0015585537_585817\u0015 ."
    },
    {
        "type": "INV",
        "text": "can you tell me how you would make a peanut butter and jelly sandwich ? \u0015585839_589189\u0015",
        "mor": "mod|can pro:per|you v|tell pro:obj|me pro:int|how pro:per|you",
        "gra": "1|3|AUX 2|3|SUBJ 3|0|ROOT 4|3|OBJ 5|8|LINK 6|8|SUBJ 7|8|AUX 8|3|COMP",
        "wor": "can \u0015585839_586109\u0015 you \u0015586109_586209\u0015 tell \u0015586209_586469\u0015 me \u0015586469_586589\u0015 how \u0015586589_586729\u0015 you \u0015586729_586929\u0015 would \u0015586929_587059\u0015 make \u0015587059_587369\u0015 a \u0015587369_587419\u0015 peanut \u0015587419_587799\u0015 butter \u0015587799_588059\u0015 and \u0015588059_588279\u0015 jelly \u0015588279_588599\u0015 sandwich \u0015588599_589189\u0015 ?"
    },
    {
        "type": "PAR",
        "text": "just take two pieces [//] slices of bread . \u0015591725_594195\u0015",
        "mor": "adv|just v|take det:num|two n|slice-PL prep|of n|bread .",
        "gra": "1|2|JCT 2|0|ROOT 3|4|QUANT 4|2|OBJ 5|4|NJCT 6|5|POBJ 7|2|PUNCT",
        "wor": "just \u0015591725_592145\u0015 take \u0015592145_592435\u0015 two \u0015592435_592545\u0015 pieces [//] \u0015592545_593015\u0015 slices \u0015593015_593615\u0015 of \u0015593615_593815\u0015 bread \u0015593815_594195\u0015 ."
    },
    {
        "type": "PAR",
        "text": "put peanut butter on one . \u0015594342_595902\u0015",
        "mor": "v|put&ZERO n|peanut n|butter adv|on pro:indef|one .",
        "gra": "1|0|ROOT 2|3|MOD 3|1|OBJ 4|1|JCT 5|4|POBJ 6|1|PUNCT",
        "wor": "put \u0015594342_594632\u0015 peanut \u0015594632_594912\u0015 butter \u0015595002_595362\u0015 on \u0015595362_595622\u0015 one \u0015595622_595902\u0015 ."
    },
    {
        "type": "PAR",
        "text": "put jam on the other . \u0015595926_597636\u0015",
        "mor": "v|put&ZERO n|jam prep|on det:art|the qn|other .",
        "gra": "1|0|ROOT 2|1|OBJ 3|1|JCT 4|5|DET 5|3|POBJ 6|1|PUNCT",
        "wor": "put \u0015595926_596616\u0015 jam \u0015596616_596876\u0015 on \u0015596876_597086\u0015 the \u0015597086_597136\u0015 other \u0015597136_597636\u0015 ."
    },
    {
        "type": "PAR",
        "text": "put them together . \u0015597789_598769\u0015",
        "mor": "v|put&ZERO pro:obj|them adv|together .",
        "gra": "1|0|ROOT 2|1|OBJ 3|1|JCT 4|1|PUNCT",
        "wor": "put \u0015597789_597929\u0015 them \u0015597929_598009\u0015 together \u0015598009_598769\u0015 ."
    },
    {
        "type": "PAR",
        "text": "just cut it into half . \u0015599803_601053\u0015",
        "mor": "adv|just v|cut&ZERO pro:per|it prep|into n|half .",
        "gra": "1|2|JCT 2|0|ROOT 3|2|OBJ 4|2|JCT 5|4|POBJ 6|2|PUNCT",
        "wor": "just \u0015599803_600083\u0015 cut \u0015600083_600393\u0015 it \u0015600393_600453\u0015 into \u0015600453_600743\u0015 half \u0015600743_601053\u0015 ."
    },
    {
        "type": "PAR",
        "text": "and that's how . \u0015601130_602220\u0015",
        "mor": "coord|and pro:rel|that~cop|be&3S pro:rel|how .",
        "gra": "1|3|LINK 2|3|LINK 3|0|ROOT 4|3|PRED 5|3|PUNCT",
        "wor": "and \u0015601130_601300\u0015 that's \u0015601770_602030\u0015 how \u0015602030_602220\u0015 ."
    },
    {
        "type": "INV",
        "text": "okay &=laughs . \u0015602811_603291\u0015",
        "mor": "co|okay .",
        "gra": "1|0|INCROOT 2|1|PUNCT",
        "wor": "okay \u0015602811_603291\u0015 &=laughs ."
    },
    {
        "type": "INV",
        "text": "good ‡ very good . \u0015603372_605102\u0015",
        "mor": "adj|good beg|beg adv|very adj|good .",
        "gra": "1|0|BEG 2|1|BEGP 3|4|JCT 4|0|INCROOT 5|4|PUNCT",
        "wor": "good \u0015603372_603992\u0015 ‡ very \u0015604632_604842\u0015 good \u0015604842_605102\u0015 ."
    },
    {
        "type": "INV",
        "text": "okay . \u0015605380_605760\u0015",
        "mor": "co|okay .",
        "gra": "1|0|INCROOT 2|1|PUNCT",
        "wor": "okay \u0015605380_605760\u0015 ."
    },
    {
        "type": "INV",
        "text": "so ‡ we're done with that task . \u0015605847_608717\u0015",
        "mor": "co|so beg|beg pro:sub|we~aux|be&PRES part|do&PASTP prep|with",
        "gra": "1|0|BEG 2|1|BEGP 3|5|SUBJ 4|5|AUX 5|0|ROOT 6|5|JCT 7|8|DET 8|6|POBJ",
        "wor": "so \u0015605847_605917\u0015 ‡ we're \u0015606757_606897\u0015 done \u0015606897_607177\u0015 with \u0015607177_607447\u0015 that \u0015607447_607737\u0015 task \u0015607737_608717\u0015 ."
    }
]